[
  {
    "city": "New York",
    "temp": -1.69,
    "humidity": 67,
    "wind": 2.57,
    "pressure": 1024,
    "timestamp": 1767617752
  },
  {
    "city": "Los Angeles",
    "temp": 11.92,
    "humidity": 95,
    "wind": 2.06,
    "pressure": 1017,
    "timestamp": 1767617905
  },
  {
    "city": "Chicago",
    "temp": 0.45,
    "humidity": 80,
    "wind": 5.66,
    "pressure": 1010,
    "timestamp": 1767617853
  },
  {
    "city": "Houston",
    "temp": 11.33,
    "humidity": 94,
    "wind": 3.6,
    "pressure": 1016,
    "timestamp": 1767617888
  },
  {
    "city": "Phoenix",
    "temp": 13.22,
    "humidity": 73,
    "wind": 2.06,
    "pressure": 1015,
    "timestamp": 1767617909
  },
  {
    "city": "Philadelphia",
    "temp": -3.07,
    "humidity": 82,
    "wind": 2.57,
    "pressure": 1024,
    "timestamp": 1767617634
  },
  {
    "city": "San Antonio",
    "temp": 14.9,
    "humidity": 90,
    "wind": 0,
    "pressure": 1015,
    "timestamp": 1767617764
  },
  {
    "city": "San Diego",
    "temp": 13.26,
    "humidity": 95,
    "wind": 2.06,
    "pressure": 1016,
    "timestamp": 1767617821
  },
  {
    "city": "Dallas",
    "temp": 9.65,
    "humidity": 90,
    "wind": 4.12,
    "pressure": 1014,
    "timestamp": 1767617661
  },
  {
    "city": "San Jose",
    "temp": 10.25,
    "humidity": 90,
    "wind": 4.63,
    "pressure": 1014,
    "timestamp": 1767617876
  },
  {
    "city": "Austin",
    "temp": 14.06,
    "humidity": 92,
    "wind": 3.58,
    "pressure": 1016,
    "timestamp": 1767617881
  },
  {
    "city": "Jacksonville",
    "temp": 10.93,
    "humidity": 96,
    "wind": 3.6,
    "pressure": 1020,
    "timestamp": 1767617918
  },
  {
    "city": "Fort Worth",
    "temp": 10.8,
    "humidity": 83,
    "wind": 5.66,
    "pressure": 1013,
    "timestamp": 1767617773
  },
  {
    "city": "Columbus",
    "temp": -2.89,
    "humidity": 78,
    "wind": 2.57,
    "pressure": 1016,
    "timestamp": 1767617757
  },
  {
    "city": "Charlotte",
    "temp": 6.3,
    "humidity": 94,
    "wind": 0,
    "pressure": 1022,
    "timestamp": 1767617598
  },
  {
    "city": "San Francisco",
    "temp": 10.77,
    "humidity": 89,
    "wind": 6.17,
    "pressure": 1013,
    "timestamp": 1767617923
  },
  {
    "city": "Indianapolis",
    "temp": -0.79,
    "humidity": 69,
    "wind": 3.09,
    "pressure": 1014,
    "timestamp": 1767617717
  },
  {
    "city": "Seattle",
    "temp": 5.9,
    "humidity": 95,
    "wind": 3.6,
    "pressure": 1008,
    "timestamp": 1767617470
  },
  {
    "city": "Denver",
    "temp": 4.41,
    "humidity": 38,
    "wind": 2.52,
    "pressure": 1006,
    "timestamp": 1767617761
  },
  {
    "city": "Washington",
    "temp": -0.52,
    "humidity": 90,
    "wind": 2.01,
    "pressure": 1009,
    "timestamp": 1767617898
  },
  {
    "city": "Boston",
    "temp": -9.65,
    "humidity": 64,
    "wind": 4.12,
    "pressure": 1024,
    "timestamp": 1767617799
  },
  {
    "city": "El Paso",
    "temp": 6.32,
    "humidity": 70,
    "wind": 2.06,
    "pressure": 1015,
    "timestamp": 1767617930
  },
  {
    "city": "Nashville",
    "temp": 0.25,
    "humidity": 79,
    "wind": 2.06,
    "pressure": 1019,
    "timestamp": 1767617830
  },
  {
    "city": "Detroit",
    "temp": -0.89,
    "humidity": 81,
    "wind": 6.69,
    "pressure": 1012,
    "timestamp": 1767617884
  },
  {
    "city": "Oklahoma City",
    "temp": 8.45,
    "humidity": 86,
    "wind": 6.69,
    "pressure": 1009,
    "timestamp": 1767617704
  },
  {
    "city": "Portland",
    "temp": 5.39,
    "humidity": 93,
    "wind": 2.68,
    "pressure": 1010,
    "timestamp": 1767617677
  },
  {
    "city": "Las Vegas",
    "temp": 11.58,
    "humidity": 65,
    "wind": 7.2,
    "pressure": 1012,
    "timestamp": 1767617937
  },
  {
    "city": "Memphis",
    "temp": 2.91,
    "humidity": 84,
    "wind": 2.06,
    "pressure": 1017,
    "timestamp": 1767617848
  },
  {
    "city": "Louisville",
    "temp": -0.46,
    "humidity": 64,
    "wind": 2.06,
    "pressure": 1017,
    "timestamp": 1767617810
  },
  {
    "city": "Baltimore",
    "temp": -2.32,
    "humidity": 77,
    "wind": 0,
    "pressure": 1024,
    "timestamp": 1767617666
  },
  {
    "city": "Milwaukee",
    "temp": -0.89,
    "humidity": 82,
    "wind": 3.09,
    "pressure": 1009,
    "timestamp": 1767617900
  },
  {
    "city": "Albuquerque",
    "temp": 3.44,
    "humidity": 68,
    "wind": 0.71,
    "pressure": 1016,
    "timestamp": 1767617695
  },
  {
    "city": "Tucson",
    "temp": 8.89,
    "humidity": 85,
    "wind": 4.12,
    "pressure": 1016,
    "timestamp": 1767617904
  },
  {
    "city": "Fresno",
    "temp": 9.61,
    "humidity": 84,
    "wind": 3.6,
    "pressure": 1016,
    "timestamp": 1767617945
  },
  {
    "city": "Mesa",
    "temp": 12.5,
    "humidity": 75,
    "wind": 2.06,
    "pressure": 1016,
    "timestamp": 1767617947
  },
  {
    "city": "Sacramento",
    "temp": 10.32,
    "humidity": 94,
    "wind": 6.17,
    "pressure": 1014,
    "timestamp": 1767617948
  },
  {
    "city": "Atlanta",
    "temp": 6.27,
    "humidity": 82,
    "wind": 2.57,
    "pressure": 1021,
    "timestamp": 1767617700
  },
  {
    "city": "Kansas City",
    "temp": 5.94,
    "humidity": 93,
    "wind": 2.57,
    "pressure": 1010,
    "timestamp": 1767617823
  },
  {
    "city": "Colorado Springs",
    "temp": 6.98,
    "humidity": 30,
    "wind": 7.72,
    "pressure": 1007,
    "timestamp": 1767617722
  },
  {
    "city": "Miami",
    "temp": 16.98,
    "humidity": 96,
    "wind": 0,
    "pressure": 1018,
    "timestamp": 1767617765
  },
  {
    "city": "Raleigh",
    "temp": 0.34,
    "humidity": 89,
    "wind": 2.1,
    "pressure": 1023,
    "timestamp": 1767617944
  },
  {
    "city": "Omaha",
    "temp": 1.67,
    "humidity": 91,
    "wind": 3.6,
    "pressure": 1007,
    "timestamp": 1767617872
  },
  {
    "city": "Long Beach",
    "temp": 11.98,
    "humidity": 98,
    "wind": 1.54,
    "pressure": 1017,
    "timestamp": 1767617957
  },
  {
    "city": "Virginia Beach",
    "temp": -2.94,
    "humidity": 86,
    "wind": 0,
    "pressure": 1024,
    "timestamp": 1767617820
  },
  {
    "city": "Oakland",
    "temp": -2.3,
    "humidity": 77,
    "wind": 3.6,
    "pressure": 1011,
    "timestamp": 1767617959
  },
  {
    "city": "Minneapolis",
    "temp": -7.53,
    "humidity": 96,
    "wind": 0,
    "pressure": 1009,
    "timestamp": 1767617570
  },
  {
    "city": "Tulsa",
    "temp": 6.1,
    "humidity": 92,
    "wind": 5.14,
    "pressure": 1011,
    "timestamp": 1767617710
  },
  {
    "city": "Tampa",
    "temp": 14.13,
    "humidity": 96,
    "wind": 3.09,
    "pressure": 1020,
    "timestamp": 1767617785
  },
  {
    "city": "New Orleans",
    "temp": 12.12,
    "humidity": 75,
    "wind": 3.09,
    "pressure": 1018,
    "timestamp": 1767617913
  },
  {
    "city": "Wichita",
    "temp": 4.92,
    "humidity": 91,
    "wind": 5.14,
    "pressure": 1007,
    "timestamp": 1767617866
  },
  {
    "city": "Arlington",
    "temp": 10.92,
    "humidity": 81,
    "wind": 5.14,
    "pressure": 1013,
    "timestamp": 1767617797
  },
  {
    "city": "Bakersfield",
    "temp": 6.09,
    "humidity": 91,
    "wind": 0.45,
    "pressure": 1016,
    "timestamp": 1767617895
  },
  {
    "city": "Aurora",
    "temp": 3.46,
    "humidity": 37,
    "wind": 4.63,
    "pressure": 1006,
    "timestamp": 1767617941
  },
  {
    "city": "Cleveland",
    "temp": -1.81,
    "humidity": 76,
    "wind": 6.69,
    "pressure": 1015,
    "timestamp": 1767617939
  },
  {
    "city": "Anaheim",
    "temp": 11.35,
    "humidity": 95,
    "wind": 1.54,
    "pressure": 1017,
    "timestamp": 1767617776
  },
  {
    "city": "Honolulu",
    "temp": 22.96,
    "humidity": 81,
    "wind": 7.72,
    "pressure": 1013,
    "timestamp": 1767617702
  },
  {
    "city": "Lexington",
    "temp": 0.9,
    "humidity": 66,
    "wind": 4.63,
    "pressure": 1017,
    "timestamp": 1767617927
  },
  {
    "city": "Stockton",
    "temp": 10.46,
    "humidity": 97,
    "wind": 5.66,
    "pressure": 1014,
    "timestamp": 1767617975
  },
  {
    "city": "Corpus Christi",
    "temp": 17.97,
    "humidity": 93,
    "wind": 2.06,
    "pressure": 1014,
    "timestamp": 1767617977
  },
  {
    "city": "Henderson",
    "temp": 12.11,
    "humidity": 61,
    "wind": 5.66,
    "pressure": 1013,
    "timestamp": 1767617978
  },
  {
    "city": "Riverside",
    "temp": 10.14,
    "humidity": 86,
    "wind": 0.42,
    "pressure": 1015,
    "timestamp": 1767617820
  },
  {
    "city": "Santa Ana",
    "temp": 11.36,
    "humidity": 95,
    "wind": 1.54,
    "pressure": 1017,
    "timestamp": 1767617980
  },
  {
    "city": "St. Louis",
    "temp": 1.02,
    "humidity": 78,
    "wind": 2.57,
    "pressure": 1013,
    "timestamp": 1767617816
  },
  {
    "city": "Pittsburgh",
    "temp": -4.22,
    "humidity": 88,
    "wind": 2.06,
    "pressure": 1020,
    "timestamp": 1767617874
  },
  {
    "city": "Cincinnati",
    "temp": -0.92,
    "humidity": 69,
    "wind": 0.89,
    "pressure": 1016,
    "timestamp": 1767617929
  },
  {
    "city": "Anchorage",
    "temp": -16.72,
    "humidity": 86,
    "wind": 6.71,
    "pressure": 981,
    "timestamp": 1767617868
  },
  {
    "city": "Greensboro",
    "temp": 1.37,
    "humidity": 83,
    "wind": 1.54,
    "pressure": 1023,
    "timestamp": 1767617987
  },
  {
    "city": "Plano",
    "temp": 9.47,
    "humidity": 90,
    "wind": 6.71,
    "pressure": 1013,
    "timestamp": 1767617861
  },
  {
    "city": "Newark",
    "temp": -3.06,
    "humidity": 73,
    "wind": 2.57,
    "pressure": 1024,
    "timestamp": 1767617540
  },
  {
    "city": "Lincoln",
    "temp": 3.1,
    "humidity": 89,
    "wind": 1.79,
    "pressure": 1006,
    "timestamp": 1767617871
  },
  {
    "city": "Orlando",
    "temp": 13.99,
    "humidity": 99,
    "wind": 2.06,
    "pressure": 1020,
    "timestamp": 1767617988
  },
  {
    "city": "Irvine",
    "temp": 11.6,
    "humidity": 95,
    "wind": 2.24,
    "pressure": 1017,
    "timestamp": 1767617970
  },
  {
    "city": "Toledo",
    "temp": 4.06,
    "humidity": 68,
    "wind": 4.81,
    "pressure": 1011,
    "timestamp": 1767617887
  },
  {
    "city": "Durham",
    "temp": -0.12,
    "humidity": 86,
    "wind": 0,
    "pressure": 1023,
    "timestamp": 1767617738
  },
  {
    "city": "Chula Vista",
    "temp": 13.35,
    "humidity": 94,
    "wind": 2.06,
    "pressure": 1016,
    "timestamp": 1767617996
  },
  {
    "city": "Fort Wayne",
    "temp": -2.25,
    "humidity": 80,
    "wind": 2.57,
    "pressure": 1012,
    "timestamp": 1767617785
  },
  {
    "city": "Jersey City",
    "temp": -2.26,
    "humidity": 72,
    "wind": 2.57,
    "pressure": 1024,
    "timestamp": 1767617998
  },
  {
    "city": "St. Petersburg",
    "temp": -13.3,
    "humidity": 87,
    "wind": 3,
    "pressure": 1016,
    "timestamp": 1767618000
  },
  {
    "city": "Laredo",
    "temp": 18.16,
    "humidity": 88,
    "wind": 4.12,
    "pressure": 1012,
    "timestamp": 1767617960
  },
  {
    "city": "Madison",
    "temp": 2.69,
    "humidity": 88,
    "wind": 1.57,
    "pressure": 1020,
    "timestamp": 1767617878
  },
  {
    "city": "Chandler",
    "temp": 11.98,
    "humidity": 77,
    "wind": 0,
    "pressure": 1015,
    "timestamp": 1767618004
  },
  {
    "city": "Buffalo",
    "temp": -3.84,
    "humidity": 87,
    "wind": 0.45,
    "pressure": 1017,
    "timestamp": 1767617983
  },
  {
    "city": "Lubbock",
    "temp": 7.14,
    "humidity": 57,
    "wind": 3.6,
    "pressure": 1011,
    "timestamp": 1767617859
  },
  {
    "city": "Scottsdale",
    "temp": 12.79,
    "humidity": 76,
    "wind": 2.06,
    "pressure": 1015,
    "timestamp": 1767617750
  },
  {
    "city": "Reno",
    "temp": 2.5,
    "humidity": 77,
    "wind": 1.54,
    "pressure": 1013,
    "timestamp": 1767618009
  },
  {
    "city": "Glendale",
    "temp": 12.31,
    "humidity": 80,
    "wind": 2.06,
    "pressure": 1015,
    "timestamp": 1767617848
  },
  {
    "city": "Gilbert",
    "temp": 12.12,
    "humidity": 76,
    "wind": 0,
    "pressure": 1016,
    "timestamp": 1767618012
  },
  {
    "city": "North Las Vegas",
    "temp": 11.77,
    "humidity": 69,
    "wind": 5.66,
    "pressure": 1013,
    "timestamp": 1767618014
  },
  {
    "city": "Norfolk",
    "temp": -9.36,
    "humidity": 66,
    "wind": 1.18,
    "pressure": 1024,
    "timestamp": 1767618016
  },
  {
    "city": "Chesapeake",
    "temp": -0.38,
    "humidity": 89,
    "wind": 0,
    "pressure": 1024,
    "timestamp": 1767617914
  },
  {
    "city": "Garland",
    "temp": 9.37,
    "humidity": 90,
    "wind": 4.63,
    "pressure": 1014,
    "timestamp": 1767617754
  },
  {
    "city": "Irving",
    "temp": 10.47,
    "humidity": 77,
    "wind": 4.12,
    "pressure": 1013,
    "timestamp": 1767617744
  },
  {
    "city": "Hialeah",
    "temp": 16.86,
    "humidity": 98,
    "wind": 1.54,
    "pressure": 1018,
    "timestamp": 1767617799
  },
  {
    "city": "Fremont",
    "temp": 10.26,
    "humidity": 91,
    "wind": 4.92,
    "pressure": 1014,
    "timestamp": 1767617903
  },
  {
    "city": "Boise",
    "temp": 3.21,
    "humidity": 90,
    "wind": 2.57,
    "pressure": 1009,
    "timestamp": 1767617935
  },
  {
    "city": "Richmond",
    "temp": -2.3,
    "humidity": 78,
    "wind": 0,
    "pressure": 1024,
    "timestamp": 1767618021
  },
  {
    "city": "Baton Rouge",
    "temp": 9.12,
    "humidity": 90,
    "wind": 1.56,
    "pressure": 1018,
    "timestamp": 1767618016
  }
]