[
  {
    "city": "New York",
    "temp": 22.85,
    "humidity": 82,
    "wind": 2.24,
    "pressure": 1007,
    "timestamp": 1749309541
  },
  {
    "city": "Los Angeles",
    "temp": 15.85,
    "humidity": 84,
    "wind": 4.12,
    "pressure": 1015,
    "timestamp": 1749309311
  },
  {
    "city": "Chicago",
    "temp": 21.27,
    "humidity": 68,
    "wind": 3.6,
    "pressure": 1013,
    "timestamp": 1749309441
  },
  {
    "city": "Houston",
    "temp": 31.02,
    "humidity": 72,
    "wind": 6.69,
    "pressure": 1013,
    "timestamp": 1749309421
  },
  {
    "city": "Phoenix",
    "temp": 30.77,
    "humidity": 18,
    "wind": 2.57,
    "pressure": 1012,
    "timestamp": 1749309667
  },
  {
    "city": "Philadelphia",
    "temp": 22.96,
    "humidity": 90,
    "wind": 2.06,
    "pressure": 1008,
    "timestamp": 1749309610
  },
  {
    "city": "San Antonio",
    "temp": 28.93,
    "humidity": 74,
    "wind": 6.17,
    "pressure": 1013,
    "timestamp": 1749309149
  },
  {
    "city": "San Diego",
    "temp": 16.71,
    "humidity": 93,
    "wind": 4.63,
    "pressure": 1015,
    "timestamp": 1749309586
  },
  {
    "city": "Dallas",
    "temp": 29.62,
    "humidity": 72,
    "wind": 1.79,
    "pressure": 1014,
    "timestamp": 1749309531
  },
  {
    "city": "San Jose",
    "temp": 16.07,
    "humidity": 82,
    "wind": 2.57,
    "pressure": 1015,
    "timestamp": 1749309067
  },
  {
    "city": "Austin",
    "temp": 29.66,
    "humidity": 73,
    "wind": 4.63,
    "pressure": 1013,
    "timestamp": 1749309582
  },
  {
    "city": "Jacksonville",
    "temp": 30.16,
    "humidity": 71,
    "wind": 6.17,
    "pressure": 1015,
    "timestamp": 1749309621
  },
  {
    "city": "Fort Worth",
    "temp": 29.43,
    "humidity": 67,
    "wind": 5.66,
    "pressure": 1014,
    "timestamp": 1749309656
  },
  {
    "city": "Columbus",
    "temp": 22.82,
    "humidity": 76,
    "wind": 4.12,
    "pressure": 1012,
    "timestamp": 1749309525
  },
  {
    "city": "Charlotte",
    "temp": 28.05,
    "humidity": 74,
    "wind": 3.09,
    "pressure": 1011,
    "timestamp": 1749309525
  },
  {
    "city": "San Francisco",
    "temp": 12.74,
    "humidity": 88,
    "wind": 4.12,
    "pressure": 1015,
    "timestamp": 1749309304
  },
  {
    "city": "Indianapolis",
    "temp": 22.26,
    "humidity": 78,
    "wind": 4.12,
    "pressure": 1012,
    "timestamp": 1749309592
  },
  {
    "city": "Seattle",
    "temp": 16.37,
    "humidity": 78,
    "wind": 3.09,
    "pressure": 1017,
    "timestamp": 1749309405
  },
  {
    "city": "Denver",
    "temp": 20.81,
    "humidity": 44,
    "wind": 0.89,
    "pressure": 1013,
    "timestamp": 1749309795
  },
  {
    "city": "Washington",
    "temp": 21.15,
    "humidity": 45,
    "wind": 1.45,
    "pressure": 1015,
    "timestamp": 1749309061
  },
  {
    "city": "Boston",
    "temp": 21.03,
    "humidity": 84,
    "wind": 0.89,
    "pressure": 1008,
    "timestamp": 1749309657
  },
  {
    "city": "El Paso",
    "temp": 28.79,
    "humidity": 14,
    "wind": 2.57,
    "pressure": 1009,
    "timestamp": 1749309686
  },
  {
    "city": "Nashville",
    "temp": 25.42,
    "humidity": 74,
    "wind": 2.06,
    "pressure": 1013,
    "timestamp": 1749309296
  },
  {
    "city": "Detroit",
    "temp": 22.29,
    "humidity": 63,
    "wind": 6.69,
    "pressure": 1013,
    "timestamp": 1749309235
  },
  {
    "city": "Oklahoma City",
    "temp": 20.47,
    "humidity": 83,
    "wind": 5.81,
    "pressure": 1010,
    "timestamp": 1749309187
  },
  {
    "city": "Portland",
    "temp": 15.89,
    "humidity": 80,
    "wind": 1.54,
    "pressure": 1017,
    "timestamp": 1749309748
  },
  {
    "city": "Las Vegas",
    "temp": 30.06,
    "humidity": 28,
    "wind": 0.89,
    "pressure": 1013,
    "timestamp": 1749309506
  },
  {
    "city": "Memphis",
    "temp": 20.9,
    "humidity": 95,
    "wind": 4.12,
    "pressure": 1013,
    "timestamp": 1749309807
  },
  {
    "city": "Louisville",
    "temp": 22.66,
    "humidity": 85,
    "wind": 1.54,
    "pressure": 1011,
    "timestamp": 1749309530
  },
  {
    "city": "Baltimore",
    "temp": 23.16,
    "humidity": 92,
    "wind": 4.12,
    "pressure": 1008,
    "timestamp": 1749309224
  },
  {
    "city": "Milwaukee",
    "temp": 19.34,
    "humidity": 57,
    "wind": 3.6,
    "pressure": 1014,
    "timestamp": 1749309626
  },
  {
    "city": "Albuquerque",
    "temp": 24.86,
    "humidity": 33,
    "wind": 2.06,
    "pressure": 1016,
    "timestamp": 1749309813
  },
  {
    "city": "Tucson",
    "temp": 28.4,
    "humidity": 23,
    "wind": 1.34,
    "pressure": 1014,
    "timestamp": 1749309727
  },
  {
    "city": "Fresno",
    "temp": 22.26,
    "humidity": 58,
    "wind": 2.57,
    "pressure": 1012,
    "timestamp": 1749309816
  },
  {
    "city": "Mesa",
    "temp": 30.36,
    "humidity": 19,
    "wind": 2.57,
    "pressure": 1012,
    "timestamp": 1749309678
  },
  {
    "city": "Sacramento",
    "temp": 17.3,
    "humidity": 74,
    "wind": 1.34,
    "pressure": 1013,
    "timestamp": 1749309642
  },
  {
    "city": "Atlanta",
    "temp": 28.04,
    "humidity": 70,
    "wind": 5.14,
    "pressure": 1014,
    "timestamp": 1749309477
  },
  {
    "city": "Kansas City",
    "temp": 21.48,
    "humidity": 90,
    "wind": 3.09,
    "pressure": 1009,
    "timestamp": 1749309298
  },
  {
    "city": "Colorado Springs",
    "temp": 19.59,
    "humidity": 45,
    "wind": 4.63,
    "pressure": 1014,
    "timestamp": 1749309700
  },
  {
    "city": "Miami",
    "temp": 31.04,
    "humidity": 70,
    "wind": 2.57,
    "pressure": 1018,
    "timestamp": 1749309256
  },
  {
    "city": "Raleigh",
    "temp": 28.02,
    "humidity": 77,
    "wind": 2.57,
    "pressure": 1010,
    "timestamp": 1749309329
  },
  {
    "city": "Omaha",
    "temp": 18.78,
    "humidity": 89,
    "wind": 2.57,
    "pressure": 1011,
    "timestamp": 1749309754
  },
  {
    "city": "Long Beach",
    "temp": 16.7,
    "humidity": 86,
    "wind": 2.57,
    "pressure": 1015,
    "timestamp": 1749309547
  },
  {
    "city": "Virginia Beach",
    "temp": 28.19,
    "humidity": 75,
    "wind": 3.09,
    "pressure": 1008,
    "timestamp": 1749309222
  },
  {
    "city": "Oakland",
    "temp": 22.29,
    "humidity": 43,
    "wind": 5.14,
    "pressure": 1013,
    "timestamp": 1749309830
  },
  {
    "city": "Minneapolis",
    "temp": 22.07,
    "humidity": 65,
    "wind": 2.57,
    "pressure": 1011,
    "timestamp": 1749309601
  },
  {
    "city": "Tulsa",
    "temp": 21.19,
    "humidity": 88,
    "wind": 2.06,
    "pressure": 1012,
    "timestamp": 1749309488
  },
  {
    "city": "Tampa",
    "temp": 30.41,
    "humidity": 70,
    "wind": 3.09,
    "pressure": 1018,
    "timestamp": 1749309310
  },
  {
    "city": "New Orleans",
    "temp": 31.02,
    "humidity": 68,
    "wind": 6.17,
    "pressure": 1015,
    "timestamp": 1749309574
  },
  {
    "city": "Wichita",
    "temp": 22.83,
    "humidity": 74,
    "wind": 6.17,
    "pressure": 1012,
    "timestamp": 1749309836
  },
  {
    "city": "Arlington",
    "temp": 29.34,
    "humidity": 64,
    "wind": 7.2,
    "pressure": 1014,
    "timestamp": 1749309838
  },
  {
    "city": "Bakersfield",
    "temp": 25.89,
    "humidity": 49,
    "wind": 0.45,
    "pressure": 1012,
    "timestamp": 1749309663
  },
  {
    "city": "Aurora",
    "temp": 20.56,
    "humidity": 42,
    "wind": 3.09,
    "pressure": 1013,
    "timestamp": 1749309630
  },
  {
    "city": "Cleveland",
    "temp": 22.18,
    "humidity": 66,
    "wind": 3.6,
    "pressure": 1012,
    "timestamp": 1749309642
  },
  {
    "city": "Anaheim",
    "temp": 17.13,
    "humidity": 81,
    "wind": 3.6,
    "pressure": 1015,
    "timestamp": 1749309660
  },
  {
    "city": "Honolulu",
    "temp": 23.39,
    "humidity": 77,
    "wind": 4.63,
    "pressure": 1015,
    "timestamp": 1749309845
  },
  {
    "city": "Lexington",
    "temp": 22.98,
    "humidity": 72,
    "wind": 1.54,
    "pressure": 1013,
    "timestamp": 1749309719
  },
  {
    "city": "Stockton",
    "temp": 18.69,
    "humidity": 74,
    "wind": 4.63,
    "pressure": 1014,
    "timestamp": 1749309730
  },
  {
    "city": "Corpus Christi",
    "temp": 30.93,
    "humidity": 73,
    "wind": 7.72,
    "pressure": 1013,
    "timestamp": 1749309603
  },
  {
    "city": "Henderson",
    "temp": 30.17,
    "humidity": 30,
    "wind": 2.06,
    "pressure": 1013,
    "timestamp": 1749309851
  },
  {
    "city": "Riverside",
    "temp": 24.02,
    "humidity": 44,
    "wind": 2.57,
    "pressure": 1011,
    "timestamp": 1749309852
  },
  {
    "city": "Santa Ana",
    "temp": 17.25,
    "humidity": 82,
    "wind": 3.6,
    "pressure": 1015,
    "timestamp": 1749309735
  },
  {
    "city": "St. Louis",
    "temp": 21.28,
    "humidity": 88,
    "wind": 0.45,
    "pressure": 1012,
    "timestamp": 1749309774
  },
  {
    "city": "Pittsburgh",
    "temp": 20.38,
    "humidity": 90,
    "wind": 2.06,
    "pressure": 1011,
    "timestamp": 1749309489
  },
  {
    "city": "Cincinnati",
    "temp": 22.19,
    "humidity": 84,
    "wind": 2.57,
    "pressure": 1011,
    "timestamp": 1749309809
  },
  {
    "city": "Anchorage",
    "temp": 7.41,
    "humidity": 86,
    "wind": 0,
    "pressure": 1006,
    "timestamp": 1749309743
  },
  {
    "city": "Greensboro",
    "temp": 24.71,
    "humidity": 85,
    "wind": 3.09,
    "pressure": 1011,
    "timestamp": 1749309860
  },
  {
    "city": "Plano",
    "temp": 29.07,
    "humidity": 72,
    "wind": 4.12,
    "pressure": 1014,
    "timestamp": 1749309618
  },
  {
    "city": "Newark",
    "temp": 23.57,
    "humidity": 81,
    "wind": 2.06,
    "pressure": 1007,
    "timestamp": 1749309710
  },
  {
    "city": "Lincoln",
    "temp": 16.42,
    "humidity": 96,
    "wind": 2.68,
    "pressure": 1009,
    "timestamp": 1749309548
  },
  {
    "city": "Orlando",
    "temp": 30.54,
    "humidity": 70,
    "wind": 2.24,
    "pressure": 1017,
    "timestamp": 1749309600
  },
  {
    "city": "Irvine",
    "temp": 17.24,
    "humidity": 85,
    "wind": 0.89,
    "pressure": 1015,
    "timestamp": 1749309730
  },
  {
    "city": "Toledo",
    "temp": 31.8,
    "humidity": 21,
    "wind": 6.89,
    "pressure": 1014,
    "timestamp": 1749309747
  },
  {
    "city": "Durham",
    "temp": 27.65,
    "humidity": 77,
    "wind": 2.57,
    "pressure": 1010,
    "timestamp": 1749309861
  },
  {
    "city": "Chula Vista",
    "temp": 16.86,
    "humidity": 93,
    "wind": 4.63,
    "pressure": 1014,
    "timestamp": 1749309761
  },
  {
    "city": "Fort Wayne",
    "temp": 22.02,
    "humidity": 61,
    "wind": 4.63,
    "pressure": 1012,
    "timestamp": 1749309757
  },
  {
    "city": "Jersey City",
    "temp": 23.53,
    "humidity": 79,
    "wind": 2.06,
    "pressure": 1007,
    "timestamp": 1749309588
  },
  {
    "city": "St. Petersburg",
    "temp": 20.03,
    "humidity": 62,
    "wind": 7,
    "pressure": 1006,
    "timestamp": 1749309760
  },
  {
    "city": "Laredo",
    "temp": 31.16,
    "humidity": 62,
    "wind": 7.72,
    "pressure": 1012,
    "timestamp": 1749309636
  },
  {
    "city": "Madison",
    "temp": 27.94,
    "humidity": 73,
    "wind": 2.57,
    "pressure": 1013,
    "timestamp": 1749309816
  },
  {
    "city": "Chandler",
    "temp": 30.42,
    "humidity": 20,
    "wind": 0.45,
    "pressure": 1012,
    "timestamp": 1749309765
  },
  {
    "city": "Buffalo",
    "temp": 22.64,
    "humidity": 65,
    "wind": 3.6,
    "pressure": 1011,
    "timestamp": 1749309650
  },
  {
    "city": "Lubbock",
    "temp": 23.14,
    "humidity": 78,
    "wind": 7.72,
    "pressure": 1012,
    "timestamp": 1749309344
  },
  {
    "city": "Scottsdale",
    "temp": 30.42,
    "humidity": 18,
    "wind": 2.57,
    "pressure": 1012,
    "timestamp": 1749309822
  },
  {
    "city": "Reno",
    "temp": 21.73,
    "humidity": 49,
    "wind": 2.57,
    "pressure": 1018,
    "timestamp": 1749309775
  },
  {
    "city": "Glendale",
    "temp": 30.51,
    "humidity": 18,
    "wind": 2.57,
    "pressure": 1012,
    "timestamp": 1749309722
  },
  {
    "city": "Gilbert",
    "temp": 30.47,
    "humidity": 19,
    "wind": 0.45,
    "pressure": 1012,
    "timestamp": 1749309887
  },
  {
    "city": "North Las Vegas",
    "temp": 30.32,
    "humidity": 27,
    "wind": 0,
    "pressure": 1013,
    "timestamp": 1749309890
  },
  {
    "city": "Norfolk",
    "temp": 21.71,
    "humidity": 88,
    "wind": 0.45,
    "pressure": 1008,
    "timestamp": 1749309891
  },
  {
    "city": "Chesapeake",
    "temp": 29.47,
    "humidity": 69,
    "wind": 3.58,
    "pressure": 1009,
    "timestamp": 1749309764
  },
  {
    "city": "Garland",
    "temp": 29.55,
    "humidity": 72,
    "wind": 4.12,
    "pressure": 1014,
    "timestamp": 1749309750
  },
  {
    "city": "Irving",
    "temp": 29.55,
    "humidity": 68,
    "wind": 7.2,
    "pressure": 1014,
    "timestamp": 1749309649
  },
  {
    "city": "Hialeah",
    "temp": 31.46,
    "humidity": 66,
    "wind": 2.57,
    "pressure": 1018,
    "timestamp": 1749309605
  },
  {
    "city": "Fremont",
    "temp": 15.2,
    "humidity": 84,
    "wind": 3.09,
    "pressure": 1015,
    "timestamp": 1749309897
  },
  {
    "city": "Boise",
    "temp": 21.29,
    "humidity": 45,
    "wind": 2.24,
    "pressure": 1017,
    "timestamp": 1749309899
  },
  {
    "city": "Richmond",
    "temp": 28.1,
    "humidity": 73,
    "wind": 3.13,
    "pressure": 1008,
    "timestamp": 1749309450
  },
  {
    "city": "Baton Rouge",
    "temp": 30.49,
    "humidity": 75,
    "wind": 5.66,
    "pressure": 1014,
    "timestamp": 1749309172
  }
]