[
  {
    "city": "New York",
    "temp": 21.18,
    "humidity": 87,
    "wind": 3.6,
    "pressure": 1013,
    "timestamp": 1757076181
  },
  {
    "city": "Los Angeles",
    "temp": 18.7,
    "humidity": 88,
    "wind": 1.54,
    "pressure": 1010,
    "timestamp": 1757075982
  },
  {
    "city": "Chicago",
    "temp": 15,
    "humidity": 74,
    "wind": 4.12,
    "pressure": 1006,
    "timestamp": 1757076131
  },
  {
    "city": "Houston",
    "temp": 26.2,
    "humidity": 88,
    "wind": 4.12,
    "pressure": 1012,
    "timestamp": 1757076140
  },
  {
    "city": "Phoenix",
    "temp": 25.9,
    "humidity": 69,
    "wind": 0.45,
    "pressure": 1011,
    "timestamp": 1757076292
  },
  {
    "city": "Philadelphia",
    "temp": 20.29,
    "humidity": 93,
    "wind": 4.63,
    "pressure": 1014,
    "timestamp": 1757076300
  },
  {
    "city": "San Antonio",
    "temp": 24.79,
    "humidity": 89,
    "wind": 4.12,
    "pressure": 1012,
    "timestamp": 1757076399
  },
  {
    "city": "San Diego",
    "temp": 19.36,
    "humidity": 92,
    "wind": 2.57,
    "pressure": 1010,
    "timestamp": 1757076179
  },
  {
    "city": "Dallas",
    "temp": 24.4,
    "humidity": 72,
    "wind": 0,
    "pressure": 1010,
    "timestamp": 1757076005
  },
  {
    "city": "San Jose",
    "temp": 17.13,
    "humidity": 81,
    "wind": 3.09,
    "pressure": 1012,
    "timestamp": 1757075666
  },
  {
    "city": "Austin",
    "temp": 25.1,
    "humidity": 86,
    "wind": 2.06,
    "pressure": 1012,
    "timestamp": 1757076148
  },
  {
    "city": "Jacksonville",
    "temp": 23.9,
    "humidity": 94,
    "wind": 1.54,
    "pressure": 1016,
    "timestamp": 1757075760
  },
  {
    "city": "Fort Worth",
    "temp": 24.7,
    "humidity": 57,
    "wind": 2.68,
    "pressure": 1010,
    "timestamp": 1757076349
  },
  {
    "city": "Columbus",
    "temp": 13.13,
    "humidity": 84,
    "wind": 3.09,
    "pressure": 1010,
    "timestamp": 1757076250
  },
  {
    "city": "Charlotte",
    "temp": 19.62,
    "humidity": 95,
    "wind": 1.54,
    "pressure": 1016,
    "timestamp": 1757076142
  },
  {
    "city": "San Francisco",
    "temp": 15.59,
    "humidity": 83,
    "wind": 8.94,
    "pressure": 1012,
    "timestamp": 1757076058
  },
  {
    "city": "Indianapolis",
    "temp": 14.66,
    "humidity": 73,
    "wind": 4.63,
    "pressure": 1009,
    "timestamp": 1757076329
  },
  {
    "city": "Seattle",
    "temp": 14.72,
    "humidity": 92,
    "wind": 0.89,
    "pressure": 1010,
    "timestamp": 1757075948
  },
  {
    "city": "Denver",
    "temp": 13.12,
    "humidity": 65,
    "wind": 1.79,
    "pressure": 1018,
    "timestamp": 1757076306
  },
  {
    "city": "Washington",
    "temp": 19.21,
    "humidity": 53,
    "wind": 1.64,
    "pressure": 1010,
    "timestamp": 1757076180
  },
  {
    "city": "Boston",
    "temp": 20.07,
    "humidity": 91,
    "wind": 2.06,
    "pressure": 1014,
    "timestamp": 1757076192
  },
  {
    "city": "El Paso",
    "temp": 18.41,
    "humidity": 81,
    "wind": 2.06,
    "pressure": 1017,
    "timestamp": 1757075708
  },
  {
    "city": "Nashville",
    "temp": 21.77,
    "humidity": 85,
    "wind": 2.06,
    "pressure": 1013,
    "timestamp": 1757075892
  },
  {
    "city": "Detroit",
    "temp": 16.22,
    "humidity": 74,
    "wind": 6.69,
    "pressure": 1005,
    "timestamp": 1757076097
  },
  {
    "city": "Oklahoma City",
    "temp": 21.67,
    "humidity": 90,
    "wind": 3.09,
    "pressure": 1011,
    "timestamp": 1757076421
  },
  {
    "city": "Portland",
    "temp": 18.44,
    "humidity": 88,
    "wind": 1.54,
    "pressure": 1010,
    "timestamp": 1757076422
  },
  {
    "city": "Las Vegas",
    "temp": 23.69,
    "humidity": 63,
    "wind": 4.12,
    "pressure": 1008,
    "timestamp": 1757076301
  },
  {
    "city": "Memphis",
    "temp": 23.02,
    "humidity": 87,
    "wind": 3.09,
    "pressure": 1012,
    "timestamp": 1757076337
  },
  {
    "city": "Louisville",
    "temp": 17.62,
    "humidity": 90,
    "wind": 2.06,
    "pressure": 1011,
    "timestamp": 1757076241
  },
  {
    "city": "Baltimore",
    "temp": 19.65,
    "humidity": 91,
    "wind": 1.54,
    "pressure": 1014,
    "timestamp": 1757076301
  },
  {
    "city": "Milwaukee",
    "temp": 13.54,
    "humidity": 69,
    "wind": 10.29,
    "pressure": 1004,
    "timestamp": 1757076213
  },
  {
    "city": "Albuquerque",
    "temp": 18.51,
    "humidity": 63,
    "wind": 4.12,
    "pressure": 1014,
    "timestamp": 1757076300
  },
  {
    "city": "Tucson",
    "temp": 22.29,
    "humidity": 71,
    "wind": 3.6,
    "pressure": 1013,
    "timestamp": 1757076300
  },
  {
    "city": "Fresno",
    "temp": 18.93,
    "humidity": 72,
    "wind": 3.09,
    "pressure": 1010,
    "timestamp": 1757076317
  },
  {
    "city": "Mesa",
    "temp": 24.81,
    "humidity": 69,
    "wind": 2.06,
    "pressure": 1011,
    "timestamp": 1757076433
  },
  {
    "city": "Sacramento",
    "temp": 15.47,
    "humidity": 86,
    "wind": 2.57,
    "pressure": 1011,
    "timestamp": 1757076150
  },
  {
    "city": "Atlanta",
    "temp": 21.56,
    "humidity": 89,
    "wind": 0.45,
    "pressure": 1016,
    "timestamp": 1757075895
  },
  {
    "city": "Kansas City",
    "temp": 15.44,
    "humidity": 81,
    "wind": 1.54,
    "pressure": 1015,
    "timestamp": 1757076324
  },
  {
    "city": "Colorado Springs",
    "temp": 12.06,
    "humidity": 79,
    "wind": 4.63,
    "pressure": 1020,
    "timestamp": 1757076230
  },
  {
    "city": "Miami",
    "temp": 27.51,
    "humidity": 88,
    "wind": 2.06,
    "pressure": 1014,
    "timestamp": 1757076414
  },
  {
    "city": "Raleigh",
    "temp": 22.65,
    "humidity": 81,
    "wind": 4.12,
    "pressure": 1016,
    "timestamp": 1757076279
  },
  {
    "city": "Omaha",
    "temp": 12.69,
    "humidity": 68,
    "wind": 5.66,
    "pressure": 1015,
    "timestamp": 1757076200
  },
  {
    "city": "Long Beach",
    "temp": 19.07,
    "humidity": 92,
    "wind": 2.06,
    "pressure": 1010,
    "timestamp": 1757076443
  },
  {
    "city": "Virginia Beach",
    "temp": 23.11,
    "humidity": 79,
    "wind": 3.09,
    "pressure": 1016,
    "timestamp": 1757076444
  },
  {
    "city": "Oakland",
    "temp": 12.66,
    "humidity": 75,
    "wind": 5.66,
    "pressure": 1005,
    "timestamp": 1757076223
  },
  {
    "city": "Minneapolis",
    "temp": 7.56,
    "humidity": 85,
    "wind": 8.75,
    "pressure": 1009,
    "timestamp": 1757076202
  },
  {
    "city": "Tulsa",
    "temp": 21.63,
    "humidity": 91,
    "wind": 2.57,
    "pressure": 1012,
    "timestamp": 1757076448
  },
  {
    "city": "Tampa",
    "temp": 25.35,
    "humidity": 94,
    "wind": 2.57,
    "pressure": 1014,
    "timestamp": 1757076038
  },
  {
    "city": "New Orleans",
    "temp": 25.73,
    "humidity": 83,
    "wind": 1.54,
    "pressure": 1014,
    "timestamp": 1757076450
  },
  {
    "city": "Wichita",
    "temp": 17.39,
    "humidity": 70,
    "wind": 7.2,
    "pressure": 1015,
    "timestamp": 1757076242
  },
  {
    "city": "Arlington",
    "temp": 24.6,
    "humidity": 61,
    "wind": 2.57,
    "pressure": 1010,
    "timestamp": 1757076374
  },
  {
    "city": "Bakersfield",
    "temp": 22.99,
    "humidity": 48,
    "wind": 2.06,
    "pressure": 1009,
    "timestamp": 1757076437
  },
  {
    "city": "Aurora",
    "temp": 12.61,
    "humidity": 62,
    "wind": 4.63,
    "pressure": 1019,
    "timestamp": 1757076367
  },
  {
    "city": "Cleveland",
    "temp": 13.44,
    "humidity": 87,
    "wind": 7.2,
    "pressure": 1009,
    "timestamp": 1757076159
  },
  {
    "city": "Anaheim",
    "temp": 19.19,
    "humidity": 90,
    "wind": 3.58,
    "pressure": 1010,
    "timestamp": 1757076457
  },
  {
    "city": "Honolulu",
    "temp": 25.06,
    "humidity": 70,
    "wind": 4.63,
    "pressure": 1016,
    "timestamp": 1757076369
  },
  {
    "city": "Lexington",
    "temp": 17.82,
    "humidity": 87,
    "wind": 3.6,
    "pressure": 1012,
    "timestamp": 1757076380
  },
  {
    "city": "Stockton",
    "temp": 15.74,
    "humidity": 88,
    "wind": 2.06,
    "pressure": 1011,
    "timestamp": 1757076461
  },
  {
    "city": "Corpus Christi",
    "temp": 26.99,
    "humidity": 87,
    "wind": 2.06,
    "pressure": 1011,
    "timestamp": 1757076344
  },
  {
    "city": "Henderson",
    "temp": 23.88,
    "humidity": 62,
    "wind": 3.6,
    "pressure": 1008,
    "timestamp": 1757076463
  },
  {
    "city": "Riverside",
    "temp": 24.54,
    "humidity": 72,
    "wind": 0,
    "pressure": 1010,
    "timestamp": 1757076465
  },
  {
    "city": "Santa Ana",
    "temp": 19.38,
    "humidity": 90,
    "wind": 3.58,
    "pressure": 1010,
    "timestamp": 1757076466
  },
  {
    "city": "St. Louis",
    "temp": 17.28,
    "humidity": 71,
    "wind": 2.06,
    "pressure": 1012,
    "timestamp": 1757076258
  },
  {
    "city": "Pittsburgh",
    "temp": 17.02,
    "humidity": 97,
    "wind": 2.57,
    "pressure": 1012,
    "timestamp": 1757076363
  },
  {
    "city": "Cincinnati",
    "temp": 15.6,
    "humidity": 79,
    "wind": 0.89,
    "pressure": 1010,
    "timestamp": 1757076353
  },
  {
    "city": "Anchorage",
    "temp": 12.74,
    "humidity": 90,
    "wind": 3.09,
    "pressure": 1012,
    "timestamp": 1757076305
  },
  {
    "city": "Greensboro",
    "temp": 18.44,
    "humidity": 97,
    "wind": 3.09,
    "pressure": 1016,
    "timestamp": 1757076346
  },
  {
    "city": "Plano",
    "temp": 24.47,
    "humidity": 71,
    "wind": 2.68,
    "pressure": 1010,
    "timestamp": 1757076336
  },
  {
    "city": "Newark",
    "temp": 20.51,
    "humidity": 92,
    "wind": 3.6,
    "pressure": 1013,
    "timestamp": 1757076287
  },
  {
    "city": "Lincoln",
    "temp": 14.22,
    "humidity": 65,
    "wind": 4.12,
    "pressure": 1015,
    "timestamp": 1757076448
  },
  {
    "city": "Orlando",
    "temp": 25.8,
    "humidity": 93,
    "wind": 2.57,
    "pressure": 1015,
    "timestamp": 1757076407
  },
  {
    "city": "Irvine",
    "temp": 19.44,
    "humidity": 91,
    "wind": 1.34,
    "pressure": 1010,
    "timestamp": 1757076478
  },
  {
    "city": "Toledo",
    "temp": 28.56,
    "humidity": 30,
    "wind": 3.14,
    "pressure": 1016,
    "timestamp": 1757076035
  },
  {
    "city": "Durham",
    "temp": 21.31,
    "humidity": 91,
    "wind": 4.12,
    "pressure": 1016,
    "timestamp": 1757076481
  },
  {
    "city": "Chula Vista",
    "temp": 19.5,
    "humidity": 91,
    "wind": 2.57,
    "pressure": 1010,
    "timestamp": 1757076482
  },
  {
    "city": "Fort Wayne",
    "temp": 14.84,
    "humidity": 75,
    "wind": 4.92,
    "pressure": 1007,
    "timestamp": 1757076281
  },
  {
    "city": "Jersey City",
    "temp": 20.85,
    "humidity": 89,
    "wind": 3.6,
    "pressure": 1013,
    "timestamp": 1757076451
  },
  {
    "city": "St. Petersburg",
    "temp": 21.14,
    "humidity": 76,
    "wind": 4,
    "pressure": 1020,
    "timestamp": 1757075729
  },
  {
    "city": "Laredo",
    "temp": 26.16,
    "humidity": 83,
    "wind": 5.14,
    "pressure": 1010,
    "timestamp": 1757076326
  },
  {
    "city": "Madison",
    "temp": 22.28,
    "humidity": 91,
    "wind": 3.58,
    "pressure": 1014,
    "timestamp": 1757076488
  },
  {
    "city": "Chandler",
    "temp": 24.55,
    "humidity": 71,
    "wind": 2.06,
    "pressure": 1011,
    "timestamp": 1757076489
  },
  {
    "city": "Buffalo",
    "temp": 14.5,
    "humidity": 84,
    "wind": 4.12,
    "pressure": 1008,
    "timestamp": 1757076337
  },
  {
    "city": "Lubbock",
    "temp": 26.14,
    "humidity": 36,
    "wind": 1.54,
    "pressure": 1011,
    "timestamp": 1757076492
  },
  {
    "city": "Scottsdale",
    "temp": 25.09,
    "humidity": 67,
    "wind": 2.06,
    "pressure": 1011,
    "timestamp": 1757076266
  },
  {
    "city": "Reno",
    "temp": 16.08,
    "humidity": 56,
    "wind": 2.06,
    "pressure": 1013,
    "timestamp": 1757076340
  },
  {
    "city": "Glendale",
    "temp": 25.86,
    "humidity": 70,
    "wind": 3.09,
    "pressure": 1011,
    "timestamp": 1757076495
  },
  {
    "city": "Gilbert",
    "temp": 24.53,
    "humidity": 71,
    "wind": 2.06,
    "pressure": 1011,
    "timestamp": 1757076496
  },
  {
    "city": "North Las Vegas",
    "temp": 24.1,
    "humidity": 63,
    "wind": 4.12,
    "pressure": 1008,
    "timestamp": 1757076499
  },
  {
    "city": "Norfolk",
    "temp": 19.89,
    "humidity": 84,
    "wind": 2.57,
    "pressure": 1014,
    "timestamp": 1757076341
  },
  {
    "city": "Chesapeake",
    "temp": 22.97,
    "humidity": 79,
    "wind": 4.12,
    "pressure": 1016,
    "timestamp": 1757076236
  },
  {
    "city": "Garland",
    "temp": 24.08,
    "humidity": 76,
    "wind": 5.14,
    "pressure": 1010,
    "timestamp": 1757076503
  },
  {
    "city": "Irving",
    "temp": 25.05,
    "humidity": 64,
    "wind": 2.06,
    "pressure": 1010,
    "timestamp": 1757075999
  },
  {
    "city": "Hialeah",
    "temp": 27.02,
    "humidity": 87,
    "wind": 2.06,
    "pressure": 1014,
    "timestamp": 1757076277
  },
  {
    "city": "Fremont",
    "temp": 16.43,
    "humidity": 87,
    "wind": 3.6,
    "pressure": 1012,
    "timestamp": 1757076506
  },
  {
    "city": "Boise",
    "temp": 18.99,
    "humidity": 51,
    "wind": 2.24,
    "pressure": 1009,
    "timestamp": 1757076354
  },
  {
    "city": "Richmond",
    "temp": 20.07,
    "humidity": 82,
    "wind": 2.57,
    "pressure": 1015,
    "timestamp": 1757076350
  },
  {
    "city": "Baton Rouge",
    "temp": 24.21,
    "humidity": 89,
    "wind": 0,
    "pressure": 1014,
    "timestamp": 1757076377
  }
]