[
  {
    "city": "New York",
    "temp": -2.76,
    "humidity": 51,
    "wind": 6.17,
    "pressure": 1022,
    "timestamp": 1766730705
  },
  {
    "city": "Los Angeles",
    "temp": 15.55,
    "humidity": 91,
    "wind": 6.17,
    "pressure": 1019,
    "timestamp": 1766730802
  },
  {
    "city": "Chicago",
    "temp": 4.64,
    "humidity": 73,
    "wind": 4.12,
    "pressure": 1012,
    "timestamp": 1766730397
  },
  {
    "city": "Houston",
    "temp": 22.03,
    "humidity": 91,
    "wind": 5.14,
    "pressure": 1018,
    "timestamp": 1766730507
  },
  {
    "city": "Phoenix",
    "temp": 16.88,
    "humidity": 77,
    "wind": 1.54,
    "pressure": 1018,
    "timestamp": 1766730907
  },
  {
    "city": "Philadelphia",
    "temp": -1.94,
    "humidity": 54,
    "wind": 3.6,
    "pressure": 1023,
    "timestamp": 1766731195
  },
  {
    "city": "San Antonio",
    "temp": 20.12,
    "humidity": 91,
    "wind": 4.12,
    "pressure": 1018,
    "timestamp": 1766731196
  },
  {
    "city": "San Diego",
    "temp": 14.23,
    "humidity": 87,
    "wind": 3.09,
    "pressure": 1020,
    "timestamp": 1766730655
  },
  {
    "city": "Dallas",
    "temp": 19.75,
    "humidity": 84,
    "wind": 1.79,
    "pressure": 1015,
    "timestamp": 1766731199
  },
  {
    "city": "San Jose",
    "temp": 12.37,
    "humidity": 82,
    "wind": 6.17,
    "pressure": 1012,
    "timestamp": 1766730600
  },
  {
    "city": "Austin",
    "temp": 18.69,
    "humidity": 88,
    "wind": 3.58,
    "pressure": 1018,
    "timestamp": 1766731105
  },
  {
    "city": "Jacksonville",
    "temp": 14.9,
    "humidity": 90,
    "wind": 2.57,
    "pressure": 1019,
    "timestamp": 1766731202
  },
  {
    "city": "Fort Worth",
    "temp": 18.97,
    "humidity": 81,
    "wind": 4.12,
    "pressure": 1015,
    "timestamp": 1766731204
  },
  {
    "city": "Columbus",
    "temp": 2.39,
    "humidity": 81,
    "wind": 6.17,
    "pressure": 1019,
    "timestamp": 1766731205
  },
  {
    "city": "Charlotte",
    "temp": 13.48,
    "humidity": 80,
    "wind": 0.89,
    "pressure": 1017,
    "timestamp": 1766731045
  },
  {
    "city": "San Francisco",
    "temp": 12.67,
    "humidity": 81,
    "wind": 10.29,
    "pressure": 1011,
    "timestamp": 1766730581
  },
  {
    "city": "Indianapolis",
    "temp": 7.98,
    "humidity": 83,
    "wind": 5.66,
    "pressure": 1014,
    "timestamp": 1766731209
  },
  {
    "city": "Seattle",
    "temp": 5.54,
    "humidity": 94,
    "wind": 1.79,
    "pressure": 1003,
    "timestamp": 1766730774
  },
  {
    "city": "Denver",
    "temp": 9.25,
    "humidity": 31,
    "wind": 0.89,
    "pressure": 1013,
    "timestamp": 1766730756
  },
  {
    "city": "Washington",
    "temp": -0.83,
    "humidity": 89,
    "wind": 1.24,
    "pressure": 1006,
    "timestamp": 1766731213
  },
  {
    "city": "Boston",
    "temp": -8.29,
    "humidity": 60,
    "wind": 8.23,
    "pressure": 1020,
    "timestamp": 1766731018
  },
  {
    "city": "El Paso",
    "temp": 14.08,
    "humidity": 52,
    "wind": 3.09,
    "pressure": 1018,
    "timestamp": 1766731215
  },
  {
    "city": "Nashville",
    "temp": 17.92,
    "humidity": 87,
    "wind": 4.63,
    "pressure": 1016,
    "timestamp": 1766731217
  },
  {
    "city": "Detroit",
    "temp": -1.01,
    "humidity": 86,
    "wind": 5.14,
    "pressure": 1021,
    "timestamp": 1766730667
  },
  {
    "city": "Oklahoma City",
    "temp": 19.64,
    "humidity": 69,
    "wind": 8.23,
    "pressure": 1009,
    "timestamp": 1766731197
  },
  {
    "city": "Portland",
    "temp": 6.07,
    "humidity": 94,
    "wind": 3.13,
    "pressure": 1003,
    "timestamp": 1766730633
  },
  {
    "city": "Las Vegas",
    "temp": 12.27,
    "humidity": 50,
    "wind": 4.12,
    "pressure": 1016,
    "timestamp": 1766730992
  },
  {
    "city": "Memphis",
    "temp": 18.1,
    "humidity": 87,
    "wind": 5.66,
    "pressure": 1015,
    "timestamp": 1766731223
  },
  {
    "city": "Louisville",
    "temp": 14.41,
    "humidity": 96,
    "wind": 2.57,
    "pressure": 1014,
    "timestamp": 1766731224
  },
  {
    "city": "Baltimore",
    "temp": 1.63,
    "humidity": 60,
    "wind": 3.6,
    "pressure": 1023,
    "timestamp": 1766730997
  },
  {
    "city": "Milwaukee",
    "temp": 3.55,
    "humidity": 79,
    "wind": 6.17,
    "pressure": 1012,
    "timestamp": 1766731227
  },
  {
    "city": "Albuquerque",
    "temp": 8.64,
    "humidity": 77,
    "wind": 1.54,
    "pressure": 1021,
    "timestamp": 1766731198
  },
  {
    "city": "Tucson",
    "temp": 15.27,
    "humidity": 78,
    "wind": 3.6,
    "pressure": 1019,
    "timestamp": 1766731229
  },
  {
    "city": "Fresno",
    "temp": 14.47,
    "humidity": 76,
    "wind": 7.72,
    "pressure": 1015,
    "timestamp": 1766730964
  },
  {
    "city": "Mesa",
    "temp": 16.46,
    "humidity": 78,
    "wind": 1.54,
    "pressure": 1018,
    "timestamp": 1766731165
  },
  {
    "city": "Sacramento",
    "temp": 12.64,
    "humidity": 90,
    "wind": 9.26,
    "pressure": 1011,
    "timestamp": 1766731171
  },
  {
    "city": "Atlanta",
    "temp": 16.81,
    "humidity": 78,
    "wind": 3.09,
    "pressure": 1018,
    "timestamp": 1766731235
  },
  {
    "city": "Kansas City",
    "temp": 16.66,
    "humidity": 85,
    "wind": 4.63,
    "pressure": 1006,
    "timestamp": 1766731236
  },
  {
    "city": "Colorado Springs",
    "temp": 8.75,
    "humidity": 40,
    "wind": 4.12,
    "pressure": 1016,
    "timestamp": 1766731004
  },
  {
    "city": "Miami",
    "temp": 19.88,
    "humidity": 86,
    "wind": 2.06,
    "pressure": 1019,
    "timestamp": 1766731239
  },
  {
    "city": "Raleigh",
    "temp": 13.43,
    "humidity": 75,
    "wind": 7.2,
    "pressure": 1019,
    "timestamp": 1766731240
  },
  {
    "city": "Omaha",
    "temp": 8.26,
    "humidity": 97,
    "wind": 3.6,
    "pressure": 1007,
    "timestamp": 1766731236
  },
  {
    "city": "Long Beach",
    "temp": 16.4,
    "humidity": 93,
    "wind": 2.57,
    "pressure": 1019,
    "timestamp": 1766731146
  },
  {
    "city": "Virginia Beach",
    "temp": 7.13,
    "humidity": 66,
    "wind": 8.23,
    "pressure": 1021,
    "timestamp": 1766731165
  },
  {
    "city": "Oakland",
    "temp": -2.54,
    "humidity": 82,
    "wind": 4.12,
    "pressure": 1020,
    "timestamp": 1766731018
  },
  {
    "city": "Minneapolis",
    "temp": 1.36,
    "humidity": 96,
    "wind": 7.72,
    "pressure": 1007,
    "timestamp": 1766731246
  },
  {
    "city": "Tulsa",
    "temp": 18.84,
    "humidity": 83,
    "wind": 8.23,
    "pressure": 1009,
    "timestamp": 1766731248
  },
  {
    "city": "Tampa",
    "temp": 16.6,
    "humidity": 96,
    "wind": 2.57,
    "pressure": 1020,
    "timestamp": 1766731249
  },
  {
    "city": "New Orleans",
    "temp": 18,
    "humidity": 82,
    "wind": 3.6,
    "pressure": 1020,
    "timestamp": 1766731097
  },
  {
    "city": "Wichita",
    "temp": 14.5,
    "humidity": 76,
    "wind": 3.6,
    "pressure": 1008,
    "timestamp": 1766731251
  },
  {
    "city": "Arlington",
    "temp": 19.33,
    "humidity": 74,
    "wind": 5.14,
    "pressure": 1015,
    "timestamp": 1766731104
  },
  {
    "city": "Bakersfield",
    "temp": 15.17,
    "humidity": 73,
    "wind": 0.45,
    "pressure": 1015,
    "timestamp": 1766730986
  },
  {
    "city": "Aurora",
    "temp": 9.16,
    "humidity": 32,
    "wind": 4.12,
    "pressure": 1013,
    "timestamp": 1766731255
  },
  {
    "city": "Cleveland",
    "temp": -0.78,
    "humidity": 77,
    "wind": 3.09,
    "pressure": 1021,
    "timestamp": 1766731257
  },
  {
    "city": "Anaheim",
    "temp": 14.94,
    "humidity": 84,
    "wind": 2.06,
    "pressure": 1019,
    "timestamp": 1766731026
  },
  {
    "city": "Honolulu",
    "temp": 22.64,
    "humidity": 72,
    "wind": 3.6,
    "pressure": 1019,
    "timestamp": 1766731200
  },
  {
    "city": "Lexington",
    "temp": 12.88,
    "humidity": 90,
    "wind": 2.06,
    "pressure": 1015,
    "timestamp": 1766731233
  },
  {
    "city": "Stockton",
    "temp": 12.75,
    "humidity": 95,
    "wind": 10.29,
    "pressure": 1012,
    "timestamp": 1766731080
  },
  {
    "city": "Corpus Christi",
    "temp": 22.59,
    "humidity": 93,
    "wind": 4.63,
    "pressure": 1018,
    "timestamp": 1766731250
  },
  {
    "city": "Henderson",
    "temp": 12.86,
    "humidity": 47,
    "wind": 5.14,
    "pressure": 1016,
    "timestamp": 1766731264
  },
  {
    "city": "Riverside",
    "temp": 11.27,
    "humidity": 67,
    "wind": 0.74,
    "pressure": 1018,
    "timestamp": 1766731266
  },
  {
    "city": "Santa Ana",
    "temp": 15.14,
    "humidity": 84,
    "wind": 2.06,
    "pressure": 1019,
    "timestamp": 1766731124
  },
  {
    "city": "St. Louis",
    "temp": 15.21,
    "humidity": 94,
    "wind": 3.09,
    "pressure": 1009,
    "timestamp": 1766731268
  },
  {
    "city": "Pittsburgh",
    "temp": -0.34,
    "humidity": 82,
    "wind": 1.54,
    "pressure": 1022,
    "timestamp": 1766731218
  },
  {
    "city": "Cincinnati",
    "temp": 7.65,
    "humidity": 80,
    "wind": 3.09,
    "pressure": 1016,
    "timestamp": 1766731142
  },
  {
    "city": "Anchorage",
    "temp": -17.92,
    "humidity": 84,
    "wind": 1.79,
    "pressure": 1019,
    "timestamp": 1766731150
  },
  {
    "city": "Greensboro",
    "temp": 14.33,
    "humidity": 79,
    "wind": 1.34,
    "pressure": 1018,
    "timestamp": 1766731273
  },
  {
    "city": "Plano",
    "temp": 19.5,
    "humidity": 83,
    "wind": 4.12,
    "pressure": 1014,
    "timestamp": 1766731275
  },
  {
    "city": "Newark",
    "temp": -3.2,
    "humidity": 53,
    "wind": 5.81,
    "pressure": 1023,
    "timestamp": 1766731163
  },
  {
    "city": "Lincoln",
    "temp": 7.62,
    "humidity": 95,
    "wind": 4.12,
    "pressure": 1007,
    "timestamp": 1766731277
  },
  {
    "city": "Orlando",
    "temp": 15.14,
    "humidity": 94,
    "wind": 0.45,
    "pressure": 1020,
    "timestamp": 1766731155
  },
  {
    "city": "Irvine",
    "temp": 15.35,
    "humidity": 85,
    "wind": 3.13,
    "pressure": 1019,
    "timestamp": 1766731061
  },
  {
    "city": "Toledo",
    "temp": 3.17,
    "humidity": 90,
    "wind": 1.48,
    "pressure": 1014,
    "timestamp": 1766731281
  },
  {
    "city": "Durham",
    "temp": 13.32,
    "humidity": 76,
    "wind": 2.24,
    "pressure": 1019,
    "timestamp": 1766731282
  },
  {
    "city": "Chula Vista",
    "temp": 13.93,
    "humidity": 83,
    "wind": 3.09,
    "pressure": 1020,
    "timestamp": 1766731025
  },
  {
    "city": "Fort Wayne",
    "temp": 0.99,
    "humidity": 87,
    "wind": 5.81,
    "pressure": 1017,
    "timestamp": 1766731285
  },
  {
    "city": "Jersey City",
    "temp": -2.91,
    "humidity": 52,
    "wind": 6.17,
    "pressure": 1022,
    "timestamp": 1766731035
  },
  {
    "city": "St. Petersburg",
    "temp": 1.14,
    "humidity": 84,
    "wind": 6,
    "pressure": 1013,
    "timestamp": 1766731288
  },
  {
    "city": "Laredo",
    "temp": 21.16,
    "humidity": 83,
    "wind": 4.12,
    "pressure": 1017,
    "timestamp": 1766731289
  },
  {
    "city": "Madison",
    "temp": 15.06,
    "humidity": 97,
    "wind": 5.36,
    "pressure": 1017,
    "timestamp": 1766731290
  },
  {
    "city": "Chandler",
    "temp": 16.16,
    "humidity": 79,
    "wind": 2.57,
    "pressure": 1018,
    "timestamp": 1766731291
  },
  {
    "city": "Buffalo",
    "temp": -6.05,
    "humidity": 73,
    "wind": 5.14,
    "pressure": 1027,
    "timestamp": 1766731293
  },
  {
    "city": "Lubbock",
    "temp": 16.14,
    "humidity": 39,
    "wind": 5.66,
    "pressure": 1017,
    "timestamp": 1766731294
  },
  {
    "city": "Scottsdale",
    "temp": 16.47,
    "humidity": 79,
    "wind": 1.54,
    "pressure": 1018,
    "timestamp": 1766731295
  },
  {
    "city": "Reno",
    "temp": 3.15,
    "humidity": 86,
    "wind": 10.8,
    "pressure": 1006,
    "timestamp": 1766731172
  },
  {
    "city": "Glendale",
    "temp": 16.2,
    "humidity": 81,
    "wind": 3.09,
    "pressure": 1018,
    "timestamp": 1766731274
  },
  {
    "city": "Gilbert",
    "temp": 16.47,
    "humidity": 79,
    "wind": 0.45,
    "pressure": 1018,
    "timestamp": 1766731258
  },
  {
    "city": "North Las Vegas",
    "temp": 12.56,
    "humidity": 50,
    "wind": 4.12,
    "pressure": 1016,
    "timestamp": 1766731302
  },
  {
    "city": "Norfolk",
    "temp": -8.31,
    "humidity": 61,
    "wind": 5.66,
    "pressure": 1020,
    "timestamp": 1766731303
  },
  {
    "city": "Chesapeake",
    "temp": 7.13,
    "humidity": 60,
    "wind": 6.69,
    "pressure": 1020,
    "timestamp": 1766731305
  },
  {
    "city": "Garland",
    "temp": 19.26,
    "humidity": 85,
    "wind": 4.63,
    "pressure": 1015,
    "timestamp": 1766731306
  },
  {
    "city": "Irving",
    "temp": 19.67,
    "humidity": 77,
    "wind": 5.14,
    "pressure": 1015,
    "timestamp": 1766731307
  },
  {
    "city": "Hialeah",
    "temp": 19.39,
    "humidity": 87,
    "wind": 2.06,
    "pressure": 1019,
    "timestamp": 1766731308
  },
  {
    "city": "Fremont",
    "temp": 12.13,
    "humidity": 87,
    "wind": 8.05,
    "pressure": 1012,
    "timestamp": 1766730918
  },
  {
    "city": "Boise",
    "temp": 8.77,
    "humidity": 72,
    "wind": 6.17,
    "pressure": 1009,
    "timestamp": 1766731202
  },
  {
    "city": "Richmond",
    "temp": 7.01,
    "humidity": 59,
    "wind": 3.6,
    "pressure": 1021,
    "timestamp": 1766731312
  },
  {
    "city": "Baton Rouge",
    "temp": 17.27,
    "humidity": 91,
    "wind": 2.57,
    "pressure": 1019,
    "timestamp": 1766731314
  }
]