[
  {
    "city": "New York",
    "temp": 4.07,
    "humidity": 50,
    "wind": 13.41,
    "pressure": 1005,
    "timestamp": 1762885536
  },
  {
    "city": "Los Angeles",
    "temp": 24.81,
    "humidity": 45,
    "wind": 0,
    "pressure": 1019,
    "timestamp": 1762885273
  },
  {
    "city": "Chicago",
    "temp": 2.27,
    "humidity": 65,
    "wind": 7.2,
    "pressure": 1009,
    "timestamp": 1762885931
  },
  {
    "city": "Houston",
    "temp": 20.72,
    "humidity": 44,
    "wind": 4.63,
    "pressure": 1026,
    "timestamp": 1762885884
  },
  {
    "city": "Phoenix",
    "temp": 26.5,
    "humidity": 25,
    "wind": 3.09,
    "pressure": 1018,
    "timestamp": 1762885942
  },
  {
    "city": "Philadelphia",
    "temp": 5.02,
    "humidity": 48,
    "wind": 12.35,
    "pressure": 1009,
    "timestamp": 1762885768
  },
  {
    "city": "San Antonio",
    "temp": 19.93,
    "humidity": 29,
    "wind": 5.66,
    "pressure": 1025,
    "timestamp": 1762885783
  },
  {
    "city": "San Diego",
    "temp": 24.72,
    "humidity": 53,
    "wind": 2.24,
    "pressure": 1018,
    "timestamp": 1762886071
  },
  {
    "city": "Dallas",
    "temp": 18.9,
    "humidity": 25,
    "wind": 6.69,
    "pressure": 1021,
    "timestamp": 1762885967
  },
  {
    "city": "San Jose",
    "temp": 22.06,
    "humidity": 55,
    "wind": 0.45,
    "pressure": 1018,
    "timestamp": 1762886065
  },
  {
    "city": "Austin",
    "temp": 20.59,
    "humidity": 30,
    "wind": 7.72,
    "pressure": 1025,
    "timestamp": 1762885599
  },
  {
    "city": "Jacksonville",
    "temp": 10.88,
    "humidity": 32,
    "wind": 5.66,
    "pressure": 1028,
    "timestamp": 1762885809
  },
  {
    "city": "Fort Worth",
    "temp": 19.61,
    "humidity": 24,
    "wind": 9.77,
    "pressure": 1020,
    "timestamp": 1762885878
  },
  {
    "city": "Columbus",
    "temp": 1.35,
    "humidity": 66,
    "wind": 7.72,
    "pressure": 1019,
    "timestamp": 1762885489
  },
  {
    "city": "Charlotte",
    "temp": 7.16,
    "humidity": 35,
    "wind": 6.17,
    "pressure": 1024,
    "timestamp": 1762885644
  },
  {
    "city": "San Francisco",
    "temp": 19.68,
    "humidity": 70,
    "wind": 2.57,
    "pressure": 1018,
    "timestamp": 1762885881
  },
  {
    "city": "Indianapolis",
    "temp": 2.82,
    "humidity": 55,
    "wind": 7.72,
    "pressure": 1014,
    "timestamp": 1762885966
  },
  {
    "city": "Seattle",
    "temp": 10.31,
    "humidity": 81,
    "wind": 2.68,
    "pressure": 1023,
    "timestamp": 1762885423
  },
  {
    "city": "Denver",
    "temp": 18.01,
    "humidity": 23,
    "wind": 3.58,
    "pressure": 1012,
    "timestamp": 1762886081
  },
  {
    "city": "Washington",
    "temp": 13.14,
    "humidity": 73,
    "wind": 1.19,
    "pressure": 1021,
    "timestamp": 1762885800
  },
  {
    "city": "Boston",
    "temp": 3.18,
    "humidity": 52,
    "wind": 7.72,
    "pressure": 999,
    "timestamp": 1762885549
  },
  {
    "city": "El Paso",
    "temp": 17.27,
    "humidity": 27,
    "wind": 3.6,
    "pressure": 1023,
    "timestamp": 1762885604
  },
  {
    "city": "Nashville",
    "temp": 7.92,
    "humidity": 35,
    "wind": 7.72,
    "pressure": 1024,
    "timestamp": 1762885445
  },
  {
    "city": "Detroit",
    "temp": 2.12,
    "humidity": 77,
    "wind": 7.2,
    "pressure": 1014,
    "timestamp": 1762885584
  },
  {
    "city": "Oklahoma City",
    "temp": 18.69,
    "humidity": 29,
    "wind": 11.32,
    "pressure": 1015,
    "timestamp": 1762885343
  },
  {
    "city": "Portland",
    "temp": 10.51,
    "humidity": 88,
    "wind": 1.79,
    "pressure": 1021,
    "timestamp": 1762886093
  },
  {
    "city": "Las Vegas",
    "temp": 21.6,
    "humidity": 21,
    "wind": 1.54,
    "pressure": 1019,
    "timestamp": 1762886094
  },
  {
    "city": "Memphis",
    "temp": 10.76,
    "humidity": 35,
    "wind": 9.26,
    "pressure": 1023,
    "timestamp": 1762885924
  },
  {
    "city": "Louisville",
    "temp": 4.1,
    "humidity": 50,
    "wind": 7.2,
    "pressure": 1020,
    "timestamp": 1762885957
  },
  {
    "city": "Baltimore",
    "temp": 6.55,
    "humidity": 40,
    "wind": 10.8,
    "pressure": 1014,
    "timestamp": 1762885568
  },
  {
    "city": "Milwaukee",
    "temp": 3.7,
    "humidity": 51,
    "wind": 8.75,
    "pressure": 1006,
    "timestamp": 1762885840
  },
  {
    "city": "Albuquerque",
    "temp": 17.08,
    "humidity": 26,
    "wind": 0.89,
    "pressure": 1021,
    "timestamp": 1762885802
  },
  {
    "city": "Tucson",
    "temp": 26.46,
    "humidity": 21,
    "wind": 1.54,
    "pressure": 1018,
    "timestamp": 1762885904
  },
  {
    "city": "Fresno",
    "temp": 19.93,
    "humidity": 58,
    "wind": 0,
    "pressure": 1019,
    "timestamp": 1762886015
  },
  {
    "city": "Mesa",
    "temp": 26.02,
    "humidity": 23,
    "wind": 3.09,
    "pressure": 1018,
    "timestamp": 1762886104
  },
  {
    "city": "Sacramento",
    "temp": 19.63,
    "humidity": 68,
    "wind": 0,
    "pressure": 1018,
    "timestamp": 1762885855
  },
  {
    "city": "Atlanta",
    "temp": 7.25,
    "humidity": 31,
    "wind": 4.63,
    "pressure": 1027,
    "timestamp": 1762885852
  },
  {
    "city": "Kansas City",
    "temp": 12.96,
    "humidity": 36,
    "wind": 6.71,
    "pressure": 1012,
    "timestamp": 1762885817
  },
  {
    "city": "Colorado Springs",
    "temp": 18.66,
    "humidity": 22,
    "wind": 5.14,
    "pressure": 1013,
    "timestamp": 1762885976
  },
  {
    "city": "Miami",
    "temp": 18.36,
    "humidity": 56,
    "wind": 6.69,
    "pressure": 1024,
    "timestamp": 1762885822
  },
  {
    "city": "Raleigh",
    "temp": 7.27,
    "humidity": 36,
    "wind": 4.63,
    "pressure": 1022,
    "timestamp": 1762885915
  },
  {
    "city": "Omaha",
    "temp": 15.12,
    "humidity": 43,
    "wind": 4.63,
    "pressure": 1010,
    "timestamp": 1762885943
  },
  {
    "city": "Long Beach",
    "temp": 19.77,
    "humidity": 82,
    "wind": 1.54,
    "pressure": 1018,
    "timestamp": 1762886113
  },
  {
    "city": "Virginia Beach",
    "temp": 6.39,
    "humidity": 35,
    "wind": 8.75,
    "pressure": 1018,
    "timestamp": 1762886115
  },
  {
    "city": "Oakland",
    "temp": 1.61,
    "humidity": 72,
    "wind": 5.81,
    "pressure": 1012,
    "timestamp": 1762886116
  },
  {
    "city": "Minneapolis",
    "temp": 8.59,
    "humidity": 58,
    "wind": 6.69,
    "pressure": 1004,
    "timestamp": 1762886030
  },
  {
    "city": "Tulsa",
    "temp": 16.53,
    "humidity": 34,
    "wind": 10.29,
    "pressure": 1015,
    "timestamp": 1762886118
  },
  {
    "city": "Tampa",
    "temp": 12.56,
    "humidity": 33,
    "wind": 2.57,
    "pressure": 1028,
    "timestamp": 1762885437
  },
  {
    "city": "New Orleans",
    "temp": 13.36,
    "humidity": 40,
    "wind": 4.12,
    "pressure": 1029,
    "timestamp": 1762885860
  },
  {
    "city": "Wichita",
    "temp": 15.01,
    "humidity": 38,
    "wind": 6.17,
    "pressure": 1013,
    "timestamp": 1762885488
  },
  {
    "city": "Arlington",
    "temp": 19.34,
    "humidity": 24,
    "wind": 9.26,
    "pressure": 1021,
    "timestamp": 1762885300
  },
  {
    "city": "Bakersfield",
    "temp": 21.14,
    "humidity": 37,
    "wind": 0,
    "pressure": 1018,
    "timestamp": 1762886124
  },
  {
    "city": "Aurora",
    "temp": 17.59,
    "humidity": 22,
    "wind": 9.77,
    "pressure": 1015,
    "timestamp": 1762885723
  },
  {
    "city": "Cleveland",
    "temp": 2.34,
    "humidity": 65,
    "wind": 10.29,
    "pressure": 1015,
    "timestamp": 1762886127
  },
  {
    "city": "Anaheim",
    "temp": 21.32,
    "humidity": 73,
    "wind": 1.54,
    "pressure": 1018,
    "timestamp": 1762886000
  },
  {
    "city": "Honolulu",
    "temp": 23.68,
    "humidity": 75,
    "wind": 6.17,
    "pressure": 1019,
    "timestamp": 1762886129
  },
  {
    "city": "Lexington",
    "temp": 3.17,
    "humidity": 55,
    "wind": 3.13,
    "pressure": 1021,
    "timestamp": 1762886129
  },
  {
    "city": "Stockton",
    "temp": 16.03,
    "humidity": 100,
    "wind": 2.57,
    "pressure": 1019,
    "timestamp": 1762885913
  },
  {
    "city": "Corpus Christi",
    "temp": 23.2,
    "humidity": 50,
    "wind": 6.69,
    "pressure": 1026,
    "timestamp": 1762886133
  },
  {
    "city": "Henderson",
    "temp": 22.23,
    "humidity": 22,
    "wind": 1.54,
    "pressure": 1019,
    "timestamp": 1762886134
  },
  {
    "city": "Riverside",
    "temp": 24.55,
    "humidity": 23,
    "wind": 0,
    "pressure": 1017,
    "timestamp": 1762886135
  },
  {
    "city": "Santa Ana",
    "temp": 22.38,
    "humidity": 66,
    "wind": 1.54,
    "pressure": 1018,
    "timestamp": 1762886137
  },
  {
    "city": "St. Louis",
    "temp": 9.89,
    "humidity": 39,
    "wind": 5.14,
    "pressure": 1013,
    "timestamp": 1762886138
  },
  {
    "city": "Pittsburgh",
    "temp": 2.43,
    "humidity": 66,
    "wind": 5.14,
    "pressure": 1016,
    "timestamp": 1762886072
  },
  {
    "city": "Cincinnati",
    "temp": 1.69,
    "humidity": 62,
    "wind": 6.17,
    "pressure": 1019,
    "timestamp": 1762885928
  },
  {
    "city": "Anchorage",
    "temp": -9.78,
    "humidity": 82,
    "wind": 1.03,
    "pressure": 1007,
    "timestamp": 1762885918
  },
  {
    "city": "Greensboro",
    "temp": 6.54,
    "humidity": 33,
    "wind": 8.75,
    "pressure": 1022,
    "timestamp": 1762886050
  },
  {
    "city": "Plano",
    "temp": 18.83,
    "humidity": 26,
    "wind": 9.83,
    "pressure": 1021,
    "timestamp": 1762886104
  },
  {
    "city": "Newark",
    "temp": 4.09,
    "humidity": 51,
    "wind": 11.83,
    "pressure": 1005,
    "timestamp": 1762885507
  },
  {
    "city": "Lincoln",
    "temp": 18.17,
    "humidity": 36,
    "wind": 0.45,
    "pressure": 1010,
    "timestamp": 1762886124
  },
  {
    "city": "Orlando",
    "temp": 12.68,
    "humidity": 35,
    "wind": 3.6,
    "pressure": 1027,
    "timestamp": 1762885970
  },
  {
    "city": "Irvine",
    "temp": 22.85,
    "humidity": 62,
    "wind": 1.85,
    "pressure": 1018,
    "timestamp": 1762886149
  },
  {
    "city": "Toledo",
    "temp": 12.62,
    "humidity": 66,
    "wind": 2.98,
    "pressure": 1014,
    "timestamp": 1762886142
  },
  {
    "city": "Durham",
    "temp": 7.58,
    "humidity": 35,
    "wind": 4.92,
    "pressure": 1022,
    "timestamp": 1762885879
  },
  {
    "city": "Chula Vista",
    "temp": 24.91,
    "humidity": 47,
    "wind": 2.57,
    "pressure": 1018,
    "timestamp": 1762886104
  },
  {
    "city": "Fort Wayne",
    "temp": 0.46,
    "humidity": 66,
    "wind": 6.26,
    "pressure": 1013,
    "timestamp": 1762886154
  },
  {
    "city": "Jersey City",
    "temp": 4.1,
    "humidity": 50,
    "wind": 13.86,
    "pressure": 1006,
    "timestamp": 1762885953
  },
  {
    "city": "St. Petersburg",
    "temp": 5.59,
    "humidity": 93,
    "wind": 2,
    "pressure": 1015,
    "timestamp": 1762885971
  },
  {
    "city": "Laredo",
    "temp": 22.16,
    "humidity": 20,
    "wind": 7.72,
    "pressure": 1024,
    "timestamp": 1762886066
  },
  {
    "city": "Madison",
    "temp": 8.31,
    "humidity": 37,
    "wind": 6.69,
    "pressure": 1026,
    "timestamp": 1762886159
  },
  {
    "city": "Chandler",
    "temp": 25.81,
    "humidity": 24,
    "wind": 0.44,
    "pressure": 1018,
    "timestamp": 1762886160
  },
  {
    "city": "Buffalo",
    "temp": 1.57,
    "humidity": 83,
    "wind": 9.26,
    "pressure": 1010,
    "timestamp": 1762885988
  },
  {
    "city": "Lubbock",
    "temp": 23.14,
    "humidity": 16,
    "wind": 7.2,
    "pressure": 1013,
    "timestamp": 1762886162
  },
  {
    "city": "Scottsdale",
    "temp": 26.4,
    "humidity": 24,
    "wind": 3.09,
    "pressure": 1018,
    "timestamp": 1762886101
  },
  {
    "city": "Reno",
    "temp": 16.7,
    "humidity": 41,
    "wind": 1.34,
    "pressure": 1020,
    "timestamp": 1762886003
  },
  {
    "city": "Glendale",
    "temp": 26.51,
    "humidity": 25,
    "wind": 3.09,
    "pressure": 1018,
    "timestamp": 1762885970
  },
  {
    "city": "Gilbert",
    "temp": 25.85,
    "humidity": 24,
    "wind": 1.34,
    "pressure": 1018,
    "timestamp": 1762885928
  },
  {
    "city": "North Las Vegas",
    "temp": 22.14,
    "humidity": 20,
    "wind": 1.54,
    "pressure": 1019,
    "timestamp": 1762885977
  },
  {
    "city": "Norfolk",
    "temp": 2.86,
    "humidity": 54,
    "wind": 7.72,
    "pressure": 999,
    "timestamp": 1762885957
  },
  {
    "city": "Chesapeake",
    "temp": 6.5,
    "humidity": 34,
    "wind": 10.29,
    "pressure": 1018,
    "timestamp": 1762886172
  },
  {
    "city": "Garland",
    "temp": 18.87,
    "humidity": 26,
    "wind": 6.69,
    "pressure": 1021,
    "timestamp": 1762886173
  },
  {
    "city": "Irving",
    "temp": 19.3,
    "humidity": 25,
    "wind": 9.26,
    "pressure": 1021,
    "timestamp": 1762885992
  },
  {
    "city": "Hialeah",
    "temp": 18.2,
    "humidity": 56,
    "wind": 6.69,
    "pressure": 1024,
    "timestamp": 1762886059
  },
  {
    "city": "Fremont",
    "temp": 20.47,
    "humidity": 65,
    "wind": 0.89,
    "pressure": 1018,
    "timestamp": 1762886177
  },
  {
    "city": "Boise",
    "temp": 12.54,
    "humidity": 58,
    "wind": 1.79,
    "pressure": 1021,
    "timestamp": 1762885885
  },
  {
    "city": "Richmond",
    "temp": 7.14,
    "humidity": 36,
    "wind": 7.72,
    "pressure": 1018,
    "timestamp": 1762885694
  },
  {
    "city": "Baton Rouge",
    "temp": 15,
    "humidity": 38,
    "wind": 0.89,
    "pressure": 1028,
    "timestamp": 1762886115
  }
]