[
  {
    "city": "New York",
    "temp": 20.35,
    "humidity": 75,
    "wind": 4.63,
    "pressure": 1016,
    "timestamp": 1756016625
  },
  {
    "city": "Los Angeles",
    "temp": 23.16,
    "humidity": 74,
    "wind": 4.12,
    "pressure": 1012,
    "timestamp": 1756017037
  },
  {
    "city": "Chicago",
    "temp": 17.11,
    "humidity": 79,
    "wind": 3.72,
    "pressure": 1015,
    "timestamp": 1756016783
  },
  {
    "city": "Houston",
    "temp": 26.1,
    "humidity": 84,
    "wind": 1.54,
    "pressure": 1013,
    "timestamp": 1756016978
  },
  {
    "city": "Phoenix",
    "temp": 36.07,
    "humidity": 36,
    "wind": 4.12,
    "pressure": 1010,
    "timestamp": 1756017004
  },
  {
    "city": "Philadelphia",
    "temp": 18.36,
    "humidity": 90,
    "wind": 0,
    "pressure": 1016,
    "timestamp": 1756016359
  },
  {
    "city": "San Antonio",
    "temp": 27.53,
    "humidity": 67,
    "wind": 3.09,
    "pressure": 1015,
    "timestamp": 1756017054
  },
  {
    "city": "San Diego",
    "temp": 21.58,
    "humidity": 88,
    "wind": 2.06,
    "pressure": 1012,
    "timestamp": 1756017021
  },
  {
    "city": "Dallas",
    "temp": 27.96,
    "humidity": 56,
    "wind": 2.06,
    "pressure": 1016,
    "timestamp": 1756016951
  },
  {
    "city": "San Jose",
    "temp": 17.71,
    "humidity": 83,
    "wind": 4.63,
    "pressure": 1013,
    "timestamp": 1756016950
  },
  {
    "city": "Austin",
    "temp": 26.57,
    "humidity": 69,
    "wind": 2.06,
    "pressure": 1016,
    "timestamp": 1756016947
  },
  {
    "city": "Jacksonville",
    "temp": 23.41,
    "humidity": 96,
    "wind": 2.06,
    "pressure": 1012,
    "timestamp": 1756017008
  },
  {
    "city": "Fort Worth",
    "temp": 26.7,
    "humidity": 55,
    "wind": 3.6,
    "pressure": 1015,
    "timestamp": 1756017010
  },
  {
    "city": "Columbus",
    "temp": 19.49,
    "humidity": 89,
    "wind": 2.57,
    "pressure": 1012,
    "timestamp": 1756017100
  },
  {
    "city": "Charlotte",
    "temp": 19.35,
    "humidity": 93,
    "wind": 0.45,
    "pressure": 1016,
    "timestamp": 1756016358
  },
  {
    "city": "San Francisco",
    "temp": 15.64,
    "humidity": 84,
    "wind": 8.23,
    "pressure": 1013,
    "timestamp": 1756016959
  },
  {
    "city": "Indianapolis",
    "temp": 19.19,
    "humidity": 77,
    "wind": 4.12,
    "pressure": 1014,
    "timestamp": 1756017085
  },
  {
    "city": "Seattle",
    "temp": 20.96,
    "humidity": 63,
    "wind": 0.45,
    "pressure": 1012,
    "timestamp": 1756016963
  },
  {
    "city": "Denver",
    "temp": 18.49,
    "humidity": 74,
    "wind": 0.45,
    "pressure": 1018,
    "timestamp": 1756017088
  },
  {
    "city": "Washington",
    "temp": 23.22,
    "humidity": 37,
    "wind": 2.04,
    "pressure": 1014,
    "timestamp": 1756017230
  },
  {
    "city": "Boston",
    "temp": 18.03,
    "humidity": 85,
    "wind": 3.6,
    "pressure": 1017,
    "timestamp": 1756017130
  },
  {
    "city": "El Paso",
    "temp": 26.49,
    "humidity": 28,
    "wind": 6.69,
    "pressure": 1017,
    "timestamp": 1756017044
  },
  {
    "city": "Nashville",
    "temp": 22.3,
    "humidity": 75,
    "wind": 0,
    "pressure": 1015,
    "timestamp": 1756016741
  },
  {
    "city": "Detroit",
    "temp": 17.35,
    "humidity": 92,
    "wind": 3.6,
    "pressure": 1011,
    "timestamp": 1756017200
  },
  {
    "city": "Oklahoma City",
    "temp": 23.25,
    "humidity": 80,
    "wind": 4.12,
    "pressure": 1017,
    "timestamp": 1756017067
  },
  {
    "city": "Portland",
    "temp": 26.01,
    "humidity": 53,
    "wind": 2.06,
    "pressure": 1011,
    "timestamp": 1756017101
  },
  {
    "city": "Las Vegas",
    "temp": 35.25,
    "humidity": 23,
    "wind": 4.63,
    "pressure": 1010,
    "timestamp": 1756016807
  },
  {
    "city": "Memphis",
    "temp": 21.86,
    "humidity": 77,
    "wind": 0,
    "pressure": 1014,
    "timestamp": 1756017240
  },
  {
    "city": "Louisville",
    "temp": 20.63,
    "humidity": 86,
    "wind": 0,
    "pressure": 1014,
    "timestamp": 1756016418
  },
  {
    "city": "Baltimore",
    "temp": 20.96,
    "humidity": 89,
    "wind": 0,
    "pressure": 1015,
    "timestamp": 1756016888
  },
  {
    "city": "Milwaukee",
    "temp": 15.89,
    "humidity": 76,
    "wind": 3.09,
    "pressure": 1014,
    "timestamp": 1756016645
  },
  {
    "city": "Albuquerque",
    "temp": 23.02,
    "humidity": 57,
    "wind": 6.17,
    "pressure": 1018,
    "timestamp": 1756017001
  },
  {
    "city": "Tucson",
    "temp": 31.48,
    "humidity": 40,
    "wind": 0.45,
    "pressure": 1013,
    "timestamp": 1756017017
  },
  {
    "city": "Fresno",
    "temp": 29.32,
    "humidity": 54,
    "wind": 2.06,
    "pressure": 1009,
    "timestamp": 1756017248
  },
  {
    "city": "Mesa",
    "temp": 35.76,
    "humidity": 35,
    "wind": 4.12,
    "pressure": 1010,
    "timestamp": 1756017020
  },
  {
    "city": "Sacramento",
    "temp": 23.75,
    "humidity": 47,
    "wind": 1.54,
    "pressure": 1011,
    "timestamp": 1756016561
  },
  {
    "city": "Atlanta",
    "temp": 20.1,
    "humidity": 83,
    "wind": 0.45,
    "pressure": 1015,
    "timestamp": 1756016909
  },
  {
    "city": "Kansas City",
    "temp": 17.47,
    "humidity": 80,
    "wind": 2.06,
    "pressure": 1020,
    "timestamp": 1756017032
  },
  {
    "city": "Colorado Springs",
    "temp": 16.07,
    "humidity": 85,
    "wind": 2.57,
    "pressure": 1025,
    "timestamp": 1756016960
  },
  {
    "city": "Miami",
    "temp": 25.24,
    "humidity": 81,
    "wind": 2.06,
    "pressure": 1015,
    "timestamp": 1756016727
  },
  {
    "city": "Raleigh",
    "temp": 20.56,
    "humidity": 90,
    "wind": 1.72,
    "pressure": 1015,
    "timestamp": 1756016668
  },
  {
    "city": "Omaha",
    "temp": 15.61,
    "humidity": 84,
    "wind": 1.54,
    "pressure": 1020,
    "timestamp": 1756017155
  },
  {
    "city": "Long Beach",
    "temp": 22.07,
    "humidity": 84,
    "wind": 3.09,
    "pressure": 1012,
    "timestamp": 1756017104
  },
  {
    "city": "Virginia Beach",
    "temp": 21.32,
    "humidity": 88,
    "wind": 3.46,
    "pressure": 1015,
    "timestamp": 1756016991
  },
  {
    "city": "Oakland",
    "temp": 15.32,
    "humidity": 86,
    "wind": 2.57,
    "pressure": 1011,
    "timestamp": 1756017023
  },
  {
    "city": "Minneapolis",
    "temp": 16.4,
    "humidity": 76,
    "wind": 5.14,
    "pressure": 1017,
    "timestamp": 1756017251
  },
  {
    "city": "Tulsa",
    "temp": 23.37,
    "humidity": 77,
    "wind": 2.06,
    "pressure": 1017,
    "timestamp": 1756017109
  },
  {
    "city": "Tampa",
    "temp": 24.75,
    "humidity": 97,
    "wind": 0,
    "pressure": 1013,
    "timestamp": 1756016978
  },
  {
    "city": "New Orleans",
    "temp": 26.92,
    "humidity": 74,
    "wind": 2.06,
    "pressure": 1012,
    "timestamp": 1756017214
  },
  {
    "city": "Wichita",
    "temp": 21.48,
    "humidity": 74,
    "wind": 4.12,
    "pressure": 1019,
    "timestamp": 1756017052
  },
  {
    "city": "Arlington",
    "temp": 26.8,
    "humidity": 55,
    "wind": 4.12,
    "pressure": 1015,
    "timestamp": 1756017217
  },
  {
    "city": "Bakersfield",
    "temp": 30.42,
    "humidity": 48,
    "wind": 2.06,
    "pressure": 1010,
    "timestamp": 1756017270
  },
  {
    "city": "Aurora",
    "temp": 18.99,
    "humidity": 71,
    "wind": 5.14,
    "pressure": 1018,
    "timestamp": 1756017067
  },
  {
    "city": "Cleveland",
    "temp": 20.19,
    "humidity": 85,
    "wind": 4.12,
    "pressure": 1011,
    "timestamp": 1756017036
  },
  {
    "city": "Anaheim",
    "temp": 22.78,
    "humidity": 80,
    "wind": 3.6,
    "pressure": 1012,
    "timestamp": 1756017274
  },
  {
    "city": "Honolulu",
    "temp": 26.14,
    "humidity": 71,
    "wind": 7.72,
    "pressure": 1016,
    "timestamp": 1756017020
  },
  {
    "city": "Lexington",
    "temp": 20.01,
    "humidity": 76,
    "wind": 1.54,
    "pressure": 1014,
    "timestamp": 1756017002
  },
  {
    "city": "Stockton",
    "temp": 21.49,
    "humidity": 67,
    "wind": 4.12,
    "pressure": 1011,
    "timestamp": 1756017278
  },
  {
    "city": "Corpus Christi",
    "temp": 26.98,
    "humidity": 82,
    "wind": 0.45,
    "pressure": 1013,
    "timestamp": 1756017279
  },
  {
    "city": "Henderson",
    "temp": 35.16,
    "humidity": 26,
    "wind": 3.6,
    "pressure": 1011,
    "timestamp": 1756017280
  },
  {
    "city": "Riverside",
    "temp": 23.36,
    "humidity": 74,
    "wind": 2.06,
    "pressure": 1011,
    "timestamp": 1756016860
  },
  {
    "city": "Santa Ana",
    "temp": 22.56,
    "humidity": 82,
    "wind": 3.6,
    "pressure": 1012,
    "timestamp": 1756017283
  },
  {
    "city": "St. Louis",
    "temp": 19.92,
    "humidity": 71,
    "wind": 3.6,
    "pressure": 1018,
    "timestamp": 1756017242
  },
  {
    "city": "Pittsburgh",
    "temp": 21.64,
    "humidity": 86,
    "wind": 3.09,
    "pressure": 1012,
    "timestamp": 1756017285
  },
  {
    "city": "Cincinnati",
    "temp": 19.64,
    "humidity": 90,
    "wind": 1.54,
    "pressure": 1013,
    "timestamp": 1756017262
  },
  {
    "city": "Anchorage",
    "temp": 14.93,
    "humidity": 81,
    "wind": 1.54,
    "pressure": 1021,
    "timestamp": 1756017288
  },
  {
    "city": "Greensboro",
    "temp": 18.53,
    "humidity": 92,
    "wind": 0.82,
    "pressure": 1015,
    "timestamp": 1756017289
  },
  {
    "city": "Plano",
    "temp": 27.19,
    "humidity": 60,
    "wind": 3.58,
    "pressure": 1015,
    "timestamp": 1756017136
  },
  {
    "city": "Newark",
    "temp": 19.24,
    "humidity": 80,
    "wind": 2.57,
    "pressure": 1016,
    "timestamp": 1756017291
  },
  {
    "city": "Lincoln",
    "temp": 16.01,
    "humidity": 84,
    "wind": 0.45,
    "pressure": 1020,
    "timestamp": 1756016613
  },
  {
    "city": "Orlando",
    "temp": 24.39,
    "humidity": 94,
    "wind": 3.6,
    "pressure": 1013,
    "timestamp": 1756016758
  },
  {
    "city": "Irvine",
    "temp": 22.59,
    "humidity": 85,
    "wind": 3.6,
    "pressure": 1012,
    "timestamp": 1756017295
  },
  {
    "city": "Toledo",
    "temp": 21.01,
    "humidity": 39,
    "wind": 0.73,
    "pressure": 1015,
    "timestamp": 1756017064
  },
  {
    "city": "Durham",
    "temp": 20.5,
    "humidity": 84,
    "wind": 0,
    "pressure": 1015,
    "timestamp": 1756017000
  },
  {
    "city": "Chula Vista",
    "temp": 21.82,
    "humidity": 87,
    "wind": 2.06,
    "pressure": 1012,
    "timestamp": 1756017051
  },
  {
    "city": "Fort Wayne",
    "temp": 15.59,
    "humidity": 96,
    "wind": 1.54,
    "pressure": 1014,
    "timestamp": 1756017278
  },
  {
    "city": "Jersey City",
    "temp": 19.97,
    "humidity": 76,
    "wind": 4.63,
    "pressure": 1016,
    "timestamp": 1756017301
  },
  {
    "city": "St. Petersburg",
    "temp": 12.25,
    "humidity": 84,
    "wind": 2,
    "pressure": 1000,
    "timestamp": 1756017040
  },
  {
    "city": "Laredo",
    "temp": 27.16,
    "humidity": 74,
    "wind": 3.09,
    "pressure": 1013,
    "timestamp": 1756017212
  },
  {
    "city": "Madison",
    "temp": 22.53,
    "humidity": 93,
    "wind": 3.58,
    "pressure": 1014,
    "timestamp": 1756017305
  },
  {
    "city": "Chandler",
    "temp": 35.42,
    "humidity": 36,
    "wind": 3.09,
    "pressure": 1010,
    "timestamp": 1756017040
  },
  {
    "city": "Buffalo",
    "temp": 20.56,
    "humidity": 76,
    "wind": 0.45,
    "pressure": 1009,
    "timestamp": 1756017024
  },
  {
    "city": "Lubbock",
    "temp": 23.14,
    "humidity": 53,
    "wind": 2.57,
    "pressure": 1019,
    "timestamp": 1756017033
  },
  {
    "city": "Scottsdale",
    "temp": 35.52,
    "humidity": 36,
    "wind": 7.15,
    "pressure": 1010,
    "timestamp": 1756017310
  },
  {
    "city": "Reno",
    "temp": 21.32,
    "humidity": 60,
    "wind": 1.54,
    "pressure": 1019,
    "timestamp": 1756017128
  },
  {
    "city": "Glendale",
    "temp": 35.46,
    "humidity": 37,
    "wind": 3.09,
    "pressure": 1010,
    "timestamp": 1756017313
  },
  {
    "city": "Gilbert",
    "temp": 35.39,
    "humidity": 36,
    "wind": 3.13,
    "pressure": 1010,
    "timestamp": 1756017314
  },
  {
    "city": "North Las Vegas",
    "temp": 35.46,
    "humidity": 23,
    "wind": 4.63,
    "pressure": 1011,
    "timestamp": 1756017049
  },
  {
    "city": "Norfolk",
    "temp": 16.74,
    "humidity": 90,
    "wind": 2.06,
    "pressure": 1017,
    "timestamp": 1756017318
  },
  {
    "city": "Chesapeake",
    "temp": 21.03,
    "humidity": 85,
    "wind": 2.06,
    "pressure": 1015,
    "timestamp": 1756017319
  },
  {
    "city": "Garland",
    "temp": 27.4,
    "humidity": 60,
    "wind": 3.58,
    "pressure": 1015,
    "timestamp": 1756017114
  },
  {
    "city": "Irving",
    "temp": 27.8,
    "humidity": 54,
    "wind": 4.12,
    "pressure": 1015,
    "timestamp": 1756017193
  },
  {
    "city": "Hialeah",
    "temp": 25.37,
    "humidity": 82,
    "wind": 2.06,
    "pressure": 1015,
    "timestamp": 1756017222
  },
  {
    "city": "Fremont",
    "temp": 17.14,
    "humidity": 86,
    "wind": 4.63,
    "pressure": 1013,
    "timestamp": 1756017324
  },
  {
    "city": "Boise",
    "temp": 23.28,
    "humidity": 43,
    "wind": 3.13,
    "pressure": 1011,
    "timestamp": 1756017325
  },
  {
    "city": "Richmond",
    "temp": 20.54,
    "humidity": 83,
    "wind": 2.57,
    "pressure": 1015,
    "timestamp": 1756017050
  },
  {
    "city": "Baton Rouge",
    "temp": 24.31,
    "humidity": 82,
    "wind": 0,
    "pressure": 1013,
    "timestamp": 1756017090
  }
]